Workbook

Sheet Financial Status
A1: Chun Wo Construction & Engineering Company Limited
Q2: Print Date: 2026-01-13
A3: Project Code: | B3: 968
A4: Project Name: | B4: Contract No. DC/2018/09 Rehabilitation of Trunk Sewers in Tuen Mun
A5: Report Date: | B5: 2025-12-31
A6: Start Date: | B6: 2018-12-28 | G6: Monthly Financial Report
A7: Complete Date: | B7: 2023-03-31 Time Consumed (%): | C7: =IFERROR((B5-B6)/(LEFT(B7, FIND(REPT(" ", 32), B7))-B6), "") | P7: Confidential
A8: Target Complete Date: | B8: 2023-12-01 Target Completed (%): | C8: =IFERROR((B5-B6)/(LEFT(B8, FIND(REPT(" ", 32), B8))-B6), "")
A11: (HK$'000) | G11: Financial Status
A12: Item | B12: Trade | C12: Budget | G12: Business Plan | H12: Audit Report (WIP) | I12: Adjustment Cost / Variation | J12: Projection | K12: Committed Value / Cost | N12: Accrual (Before Retention) | O12: Cash Flow
C13: Tender | D13: 1st Working Budget | E13: Adjustment Cost/ variation | F13: Revision as at | O13: Actual received & paid | Q13: Balance to
J14: as at | K14: as at | L14: % of time elapse | M14: Balance | N14: as at | O14: as at | P14: % of time elapse
C15: A | D15: B | E15: C | F15: D=B+C | H15: J | I15: k=I-J | J15: I | K15: E | L15: E1=E/D | M15: F=D-E | O15: G | P15: G1=G/E | Q15: H=E-G
A16: 1 | B16: Income | I16: =IF(H16="", "", J16-H16) | J16: =IF(ISBLANK(Projection!P13), "", Projection!P13) | K16: =IF(ISBLANK('Committed Cost'!P13), "", 'Committed Cost'!P13) | L16: =IFERROR(IF(ISBLANK(F16), "", K16/F16), 0) | M16: =IF(F16="", "", F16-K16) | N16: =IF(ISBLANK(Accrual!P13), "", Accrual!P13) | O16: =IF(ISBLANK('Cash Flow'!P13), "",'Cash Flow'!P13) | P16: =IFERROR(IF(O16="", "", O16/K16), 0) | Q16: =IF(K16="", "", K16-O16)
A17: 1.1 | B17: Original Contract Works | C17: 205000 | D17: 205000 | E17: 0 | F17: =D17+E17 -> 205000 | G17: 205000 | H17: 205000 | I17: =IF(H17="", "", J17-H17) -> 0 | J17: =IF(ISBLANK(Projection!P14), "", Projection!P14) -> 205000 | K17: =IF(ISBLANK('Committed Cost'!P14), "", 'Committed Cost'!P14) -> 205000 | L17: =IFERROR(IF(ISBLANK(F17), "", K17/F17), 0) -> 1 | M17: =IF(F17="", "", F17-K17) -> 0 | N17: =IF(ISBLANK(Accrual!P14), "", Accrual!P14) -> 428279.83 | O17: =IF(ISBLANK('Cash Flow'!P14), "",'Cash Flow'!P14) -> 428280.16 | P17: =IFERROR(IF(O17="", "", O17/K17), 0) -> 2.0891715 | Q17: =IF(K17="", "", K17-O17) -> -223280.16
A18: 1.2 | B18: V.O. / Compensation Events | I18: =IF(H18="", "", J18-H18) | J18: =IF(ISBLANK(Projection!P15), "", Projection!P15) | K18: =IF(ISBLANK('Committed Cost'!P15), "", 'Committed Cost'!P15) | L18: =IFERROR(IF(ISBLANK(F18), "", K18/F18), 0) | M18: =IF(F18="", "", F18-K18) | N18: =IF(ISBLANK(Accrual!P15), "", Accrual!P15) | O18: =IF(ISBLANK('Cash Flow'!P15), "",'Cash Flow'!P15) | P18: =IFERROR(IF(O18="", "", O18/K18), 0) | Q18: =IF(K18="", "", K18-O18)
A19: 1.2.1 | B19: -V.O. / C.E. | C19: 5476.51 | D19: 25383.56 | E19: 0 | F19: =D19+E19 -> 25383.56 | G19: 126723.4 | H19: 126723.4 | I19: =IF(H19="", "", J19-H19) -> 0 | J19: =IF(ISBLANK(Projection!P16), "", Projection!P16) -> 126723.4 | K19: =IF(ISBLANK('Committed Cost'!P16), "", 'Committed Cost'!P16) -> 71713.6 | L19: =IFERROR(IF(ISBLANK(F19), "", K19/F19), 0) -> 2.8251987 | M19: =IF(F19="", "", F19-K19) -> -46330.04 | N19: =IF(ISBLANK(Accrual!P16), "", Accrual!P16) -> 0 | O19: =IF(ISBLANK('Cash Flow'!P16), "",'Cash Flow'!P16) -> 0 | P19: =IFERROR(IF(O19="", "", O19/K19), 0) -> 0 | Q19: =IF(K19="", "", K19-O19) -> 71713.6
A20: 1.2.2 | B20: -Fee of C.E. | C20: 0 | D20: 0 | E20: 0 | F20: =D20+E20 -> 0 | G20: 25480.08 | H20: 25480.08 | I20: =IF(H20="", "", J20-H20) -> 0 | J20: =IF(ISBLANK(Projection!P17), "", Projection!P17) -> 25480.08 | K20: =IF(ISBLANK('Committed Cost'!P17), "", 'Committed Cost'!P17) -> 14311.16 | L20: =IFERROR(IF(ISBLANK(F20), "", K20/F20), 0) -> 0 | M20: =IF(F20="", "", F20-K20) -> -14311.16 | N20: =IF(ISBLANK(Accrual!P17), "", Accrual!P17) -> 0 | O20: =IF(ISBLANK('Cash Flow'!P17), "",'Cash Flow'!P17) -> 0 | P20: =IFERROR(IF(O20="", "", O20/K20), 0) -> 0 | Q20: =IF(K20="", "", K20-O20) -> 14311.16
A21: 1.3 | B21: Provisional Sum | C21: 0 | D21: 0 | E21: 0 | F21: =D21+E21 -> 0 | G21: 0 | H21: 0 | I21: =IF(H21="", "", J21-H21) -> 0 | J21: =IF(ISBLANK(Projection!P18), "", Projection!P18) -> 0 | K21: =IF(ISBLANK('Committed Cost'!P18), "", 'Committed Cost'!P18) -> 0 | L21: =IFERROR(IF(ISBLANK(F21), "", K21/F21), 0) -> 0 | M21: =IF(F21="", "", F21-K21) -> 0 | N21: =IF(ISBLANK(Accrual!P18), "", Accrual!P18) -> 0 | O21: =IF(ISBLANK('Cash Flow'!P18), "",'Cash Flow'!P18) -> 0 | P21: =IFERROR(IF(O21="", "", O21/K21), 0) -> 0 | Q21: =IF(K21="", "", K21-O21) -> 0
A22: 1.4 | B22: Adjustment for Provisional Quantities (remeasurement) and PC Rates | C22: 0 | D22: 0 | E22: 0 | F22: =D22+E22 -> 0 | G22: 0 | H22: 0 | I22: =IF(H22="", "", J22-H22) -> 0 | J22: =IF(ISBLANK(Projection!P19), "", Projection!P19) -> 0 | K22: =IF(ISBLANK('Committed Cost'!P19), "", 'Committed Cost'!P19) -> 0 | L22: =IFERROR(IF(ISBLANK(F22), "", K22/F22), 0) -> 0 | M22: =IF(F22="", "", F22-K22) -> 0 | N22: =IF(ISBLANK(Accrual!P19), "", Accrual!P19) -> 0 | O22: =IF(ISBLANK('Cash Flow'!P19), "",'Cash Flow'!P19) -> 0 | P22: =IFERROR(IF(O22="", "", O22/K22), 0) -> 0 | Q22: =IF(K22="", "", K22-O22) -> 0
A23: 1.5 | B23: NSC | C23: 0 | D23: 0 | E23: 0 | F23: =D23+E23 -> 0 | G23: 0 | H23: 0 | I23: =IF(H23="", "", J23-H23) -> 0 | J23: =IF(ISBLANK(Projection!P20), "", Projection!P20) -> 0 | K23: =IF(ISBLANK('Committed Cost'!P20), "", 'Committed Cost'!P20) -> 0 | L23: =IFERROR(IF(ISBLANK(F23), "", K23/F23), 0) -> 0 | M23: =IF(F23="", "", F23-K23) -> 0 | N23: =IF(ISBLANK(Accrual!P20), "", Accrual!P20) -> 0 | O23: =IF(ISBLANK('Cash Flow'!P20), "",'Cash Flow'!P20) -> 0 | P23: =IFERROR(IF(O23="", "", O23/K23), 0) -> 0 | Q23: =IF(K23="", "", K23-O23) -> 0
A24: 1.6 | B24: Profit & Attendance | C24: 0 | D24: 0 | E24: 0 | F24: =D24+E24 -> 0 | G24: 0 | H24: 0 | I24: =IF(H24="", "", J24-H24) -> 0 | J24: =IF(ISBLANK(Projection!P21), "", Projection!P21) -> 0 | K24: =IF(ISBLANK('Committed Cost'!P21), "", 'Committed Cost'!P21) -> 0 | L24: =IFERROR(IF(ISBLANK(F24), "", K24/F24), 0) -> 0 | M24: =IF(F24="", "", F24-K24) -> 0 | N24: =IF(ISBLANK(Accrual!P21), "", Accrual!P21) -> 0 | O24: =IF(ISBLANK('Cash Flow'!P21), "",'Cash Flow'!P21) -> 0 | P24: =IFERROR(IF(O24="", "", O24/K24), 0) -> 0 | Q24: =IF(K24="", "", K24-O24) -> 0
A25: 1.7 | B25: Claims | C25: 0 | D25: 0 | E25: 0 | F25: =D25+E25 -> 0 | G25: 0 | H25: 0 | I25: =IF(H25="", "", J25-H25) -> 0 | J25: =IF(ISBLANK(Projection!P22), "", Projection!P22) -> 0 | K25: =IF(ISBLANK('Committed Cost'!P22), "", 'Committed Cost'!P22) -> 0 | L25: =IFERROR(IF(ISBLANK(F25), "", K25/F25), 0) -> 0 | M25: =IF(F25="", "", F25-K25) -> 0 | N25: =IF(ISBLANK(Accrual!P22), "", Accrual!P22) -> 0 | O25: =IF(ISBLANK('Cash Flow'!P22), "",'Cash Flow'!P22) -> 0 | P25: =IFERROR(IF(O25="", "", O25/K25), 0) -> 0 | Q25: =IF(K25="", "", K25-O25) -> 0
A26: 1.8 | B26: Price Fluctuation / CPF | C26: 6124.68 | D26: 13371.87 | E26: 0 | F26: =D26+E26 -> 13371.87 | G26: 52516.54 | H26: 52516.54 | I26: =IF(H26="", "", J26-H26) -> 0 | J26: =IF(ISBLANK(Projection!P23), "", Projection!P23) -> 52516.54 | K26: =IF(ISBLANK('Committed Cost'!P23), "", 'Committed Cost'!P23) -> 52429.896 | L26: =IFERROR(IF(ISBLANK(F26), "", K26/F26), 0) -> 3.9209098 | M26: =IF(F26="", "", F26-K26) -> -39058.026 | N26: =IF(ISBLANK(Accrual!P23), "", Accrual!P23) -> 0 | O26: =IF(ISBLANK('Cash Flow'!P23), "",'Cash Flow'!P23) -> 0 | P26: =IFERROR(IF(O26="", "", O26/K26), 0) -> 0 | Q26: =IF(K26="", "", K26-O26) -> 52429.896
A27: 1.9 | B27: MPF Reimbursement | C27: 0 | D27: 0 | E27: 0 | F27: =D27+E27 -> 0 | G27: 0 | H27: 0 | I27: =IF(H27="", "", J27-H27) -> 0 | J27: =IF(ISBLANK(Projection!P24), "", Projection!P24) -> 0 | K27: =IF(ISBLANK('Committed Cost'!P24), "", 'Committed Cost'!P24) -> 0 | L27: =IFERROR(IF(ISBLANK(F27), "", K27/F27), 0) -> 0 | M27: =IF(F27="", "", F27-K27) -> 0 | N27: =IF(ISBLANK(Accrual!P24), "", Accrual!P24) -> 0 | O27: =IF(ISBLANK('Cash Flow'!P24), "",'Cash Flow'!P24) -> 0 | P27: =IFERROR(IF(O27="", "", O27/K27), 0) -> 0 | Q27: =IF(K27="", "", K27-O27) -> 0
A28: 1.10 | B28: SA | C28: 0 | D28: 0 | E28: 0 | F28: =D28+E28 -> 0 | G28: 0 | H28: 0 | I28: =IF(H28="", "", J28-H28) -> 0 | J28: =IF(ISBLANK(Projection!P25), "", Projection!P25) -> 0 | K28: =IF(ISBLANK('Committed Cost'!P25), "", 'Committed Cost'!P25) -> 0 | L28: =IFERROR(IF(ISBLANK(F28), "", K28/F28), 0) -> 0 | M28: =IF(F28="", "", F28-K28) -> 0 | N28: =IF(ISBLANK(Accrual!P25), "", Accrual!P25) -> 0 | O28: =IF(ISBLANK('Cash Flow'!P25), "",'Cash Flow'!P25) -> 0.008 | P28: =IFERROR(IF(O28="", "", O28/K28), 0) -> 0 | Q28: =IF(K28="", "", K28-O28) -> -0.008
A29: 1.11 | B29: CSD | C29: 0 | D29: 0 | E29: 0 | F29: =D29+E29 -> 0 | G29: 0 | H29: 0 | I29: =IF(H29="", "", J29-H29) -> 0 | J29: =IF(ISBLANK(Projection!P26), "", Projection!P26) -> 0 | K29: =IF(ISBLANK('Committed Cost'!P26), "", 'Committed Cost'!P26) -> 0 | L29: =IFERROR(IF(ISBLANK(F29), "", K29/F29), 0) -> 0 | M29: =IF(F29="", "", F29-K29) -> 0 | N29: =IF(ISBLANK(Accrual!P26), "", Accrual!P26) -> 0 | O29: =IF(ISBLANK('Cash Flow'!P26), "",'Cash Flow'!P26) -> 0 | P29: =IFERROR(IF(O29="", "", O29/K29), 0) -> 0 | Q29: =IF(K29="", "", K29-O29) -> 0
A30: 1.12 | B30: Other Revenue / Pain Gain Sharing | I30: =IF(H30="", "", J30-H30) | J30: =IF(ISBLANK(Projection!P27), "", Projection!P27) | K30: =IF(ISBLANK('Committed Cost'!P27), "", 'Committed Cost'!P27) | L30: =IFERROR(IF(ISBLANK(F30), "", K30/F30), 0) | M30: =IF(F30="", "", F30-K30) | N30: =IF(ISBLANK(Accrual!P27), "", Accrual!P27) | O30: =IF(ISBLANK('Cash Flow'!P27), "",'Cash Flow'!P27) | P30: =IFERROR(IF(O30="", "", O30/K30), 0) | Q30: =IF(K30="", "", K30-O30)
A31: 1.12.1 | B31: -Other Revenue | C31: 12333 | D31: 12089.6 | E31: 0 | F31: =D31+E31 -> 12089.6 | G31: 3067.819 | H31: 3067.819 | I31: =IF(H31="", "", J31-H31) -> 0 | J31: =IF(ISBLANK(Projection!P28), "", Projection!P28) -> 3067.819 | K31: =IF(ISBLANK('Committed Cost'!P28), "", 'Committed Cost'!P28) -> 2966.76 | L31: =IFERROR(IF(ISBLANK(F31), "", K31/F31), 0) -> 0.2453977 | M31: =IF(F31="", "", F31-K31) -> 9122.84 | N31: =IF(ISBLANK(Accrual!P28), "", Accrual!P28) -> -0.14 | O31: =IF(ISBLANK('Cash Flow'!P28), "",'Cash Flow'!P28) -> -0.038 | P31: =IFERROR(IF(O31="", "", O31/K31), 0) -> -1.2808586e-05 | Q31: =IF(K31="", "", K31-O31) -> 2966.798
A32: 1.12.2 | B32: -Pain Gain Sharing | C32: 0 | D32: 0 | E32: 0 | F32: =D32+E32 -> 0 | G32: 15492.6 | H32: 15492.6 | I32: =IF(H32="", "", J32-H32) -> 0 | J32: =IF(ISBLANK(Projection!P29), "", Projection!P29) -> 15492.6 | K32: =IF(ISBLANK('Committed Cost'!P29), "", 'Committed Cost'!P29) -> -48534.786 | L32: =IFERROR(IF(ISBLANK(F32), "", K32/F32), 0) -> 0 | M32: =IF(F32="", "", F32-K32) -> 48534.786 | N32: =IF(ISBLANK(Accrual!P29), "", Accrual!P29) -> 0.19949 | O32: =IF(ISBLANK('Cash Flow'!P29), "",'Cash Flow'!P29) -> -0.20051 | P32: =IFERROR(IF(O32="", "", O32/K32), 0) -> 4.1312637e-06 | Q32: =IF(K32="", "", K32-O32) -> -48534.585
A33: 1.12.3 | B33: -Stretch Target Income | C33: 0 | D33: 0 | E33: 0 | F33: =D33+E33 -> 0 | G33: 0 | H33: 0 | I33: =IF(H33="", "", J33-H33) -> 0 | J33: =IF(ISBLANK(Projection!P30), "", Projection!P30) -> 0 | K33: =IF(ISBLANK('Committed Cost'!P30), "", 'Committed Cost'!P30) -> 0 | L33: =IFERROR(IF(ISBLANK(F33), "", K33/F33), 0) -> 0 | M33: =IF(F33="", "", F33-K33) -> 0 | N33: =IF(ISBLANK(Accrual!P30), "", Accrual!P30) -> 0 | O33: =IF(ISBLANK('Cash Flow'!P30), "",'Cash Flow'!P30) -> 0 | P33: =IFERROR(IF(O33="", "", O33/K33), 0) -> 0 | Q33: =IF(K33="", "", K33-O33) -> 0
A34: 1.13 | B34: Less :LD | C34: 0 | D34: 0 | E34: 0 | F34: =D34+E34 -> 0 | G34: 0 | H34: 0 | I34: =IF(H34="", "", J34-H34) -> 0 | J34: =IF(ISBLANK(Projection!P31), "", Projection!P31) -> 0 | K34: =IF(ISBLANK('Committed Cost'!P31), "", 'Committed Cost'!P31) -> 0 | L34: =IFERROR(IF(ISBLANK(F34), "", K34/F34), 0) -> 0 | M34: =IF(F34="", "", F34-K34) -> 0 | N34: =IF(ISBLANK(Accrual!P31), "", Accrual!P31) -> 0 | O34: =IF(ISBLANK('Cash Flow'!P31), "",'Cash Flow'!P31) -> 0 | P34: =IFERROR(IF(O34="", "", O34/K34), 0) -> 0 | Q34: =IF(K34="", "", K34-O34) -> 0
A35: 1.14 | B35: Less :Retention Money | C35: 0 | D35: 0 | E35: 0 | F35: =D35+E35 -> 0 | G35: 0 | H35: 0 | I35: =IF(H35="", "", J35-H35) -> 0 | J35: =IF(ISBLANK(Projection!P32), "", Projection!P32) -> 0 | K35: =IF(ISBLANK('Committed Cost'!P32), "", 'Committed Cost'!P32) -> 0 | L35: =IFERROR(IF(ISBLANK(F35), "", K35/F35), 0) -> 0 | M35: =IF(F35="", "", F35-K35) -> 0 | N35: =IF(ISBLANK(Accrual!P32), "", Accrual!P32) -> 0 | O35: =IF(ISBLANK('Cash Flow'!P32), "",'Cash Flow'!P32) -> -0.24791 | P35: =IFERROR(IF(O35="", "", O35/K35), 0) -> 0 | Q35: =IF(K35="", "", K35-O35) -> 0.24791
A36: 1.15 | B36: Less :Retention Money (NSC) | C36: 0 | D36: 0 | E36: 0 | F36: =D36+E36 -> 0 | G36: 0 | H36: 0 | I36: =IF(H36="", "", J36-H36) -> 0 | J36: =IF(ISBLANK(Projection!P33), "", Projection!P33) -> 0 | K36: =IF(ISBLANK('Committed Cost'!P33), "", 'Committed Cost'!P33) -> 0 | L36: =IFERROR(IF(ISBLANK(F36), "", K36/F36), 0) -> 0 | M36: =IF(F36="", "", F36-K36) -> 0 | N36: =IF(ISBLANK(Accrual!P33), "", Accrual!P33) -> 0 | O36: =IF(ISBLANK('Cash Flow'!P33), "",'Cash Flow'!P33) -> 0 | P36: =IFERROR(IF(O36="", "", O36/K36), 0) -> 0 | Q36: =IF(K36="", "", K36-O36) -> 0
A37: 1.16 | B37: Partialing Income Total | C37: 0 | D37: 0 | E37: 0 | F37: =D37+E37 -> 0 | G37: 0 | H37: 0 | I37: =IF(H37="", "", J37-H37) -> 0 | J37: =IF(ISBLANK(Projection!P34), "", Projection!P34) -> 0 | K37: =IF(ISBLANK('Committed Cost'!P34), "", 'Committed Cost'!P34) -> 0 | L37: =IFERROR(IF(ISBLANK(F37), "", K37/F37), 0) -> 0 | M37: =IF(F37="", "", F37-K37) -> 0 | N37: =IF(ISBLANK(Accrual!P34), "", Accrual!P34) -> 0 | O37: =IF(ISBLANK('Cash Flow'!P34), "",'Cash Flow'!P34) -> 0 | P37: =IFERROR(IF(O37="", "", O37/K37), 0) -> 0 | Q37: =IF(K37="", "", K37-O37) -> 0
A38: 1.17 | B38: Advance Payment | C38: 0 | D38: 0 | E38: 0 | F38: 0 | G38: 0 | H38: 0 | I38: =IF(H38="", "", J38-H38) -> 0 | J38: =IF(ISBLANK(Projection!P35), "", Projection!P35) -> 0 | K38: =IF(ISBLANK('Committed Cost'!P35), "", 'Committed Cost'!P35) -> 0 | L38: =IFERROR(IF(ISBLANK(F38), "", K38/F38), 0) -> 0 | M38: =IF(F38="", "", F38-K38) -> 0 | N38: =IF(ISBLANK(Accrual!P35), "", Accrual!P35) -> 0 | O38: =IF(ISBLANK('Cash Flow'!P35), "",'Cash Flow'!P35) -> 0 | P38: =IFERROR(IF(O38="", "", O38/K38), 0) -> 0 | Q38: =IF(K38="", "", K38-O38) -> 0
B39: Total Income | C39: =SUM(C15:C38) -> 228934.19 | D39: =SUM(D15:D38) -> 255845.03 | E39: =SUM(E15:E38) -> 0 | F39: =SUM(F15:F38) -> 255845.03 | G39: =SUM(G15:G38) -> 428280.44 | H39: =SUM(H15:H38) -> 428280.44 | I39: =IF(H39="", "", J39-H39) -> 0 | J39: =IF(ISBLANK(Projection!P36), "", Projection!P36) -> 428280.44 | K39: =IF(ISBLANK('Committed Cost'!P36), "", 'Committed Cost'!P36) -> 297886.63 | L39: =IFERROR(IF(ISBLANK(F39), "", K39/F39), 0) -> 1.1643245 | M39: =IF(F39="", "", F39-K39) -> -42041.6 | N39: =IF(ISBLANK(Accrual!P36), "", Accrual!P36) -> 428279.89 | O39: =IF(ISBLANK('Cash Flow'!P36), "",'Cash Flow'!P36) -> 428279.69 | P39: =IFERROR(IF(O39="", "", O39/K39), 0) -> 1.4377271 | Q39: =IF(K39="", "", K39-O39) -> -130393.06
I40: =IF(H40="", "", J40-H40) | J40: =IF(ISBLANK(Projection!P37), "", Projection!P37) | K40: =IF(ISBLANK('Committed Cost'!P37), "", 'Committed Cost'!P37) | L40: =IFERROR(IF(ISBLANK(F40), "", K40/F40), 0) | M40: =IF(F40="", "", F40-K40) | N40: =IF(ISBLANK(Accrual!P37), "", Accrual!P37) | O40: =IF(ISBLANK('Cash Flow'!P37), "",'Cash Flow'!P37) | P40: =IFERROR(IF(O40="", "", O40/K40), 0) | Q40: =IF(K40="", "", K40-O40)
A41: 2 | B41: Less : Cost | I41: =IF(H41="", "", J41-H41) | J41: =IF(ISBLANK(Projection!P38), "", Projection!P38) | K41: =IF(ISBLANK('Committed Cost'!P38), "", 'Committed Cost'!P38) | L41: =IFERROR(IF(ISBLANK(F41), "", K41/F41), 0) | M41: =IF(F41="", "", F41-K41) | N41: =IF(ISBLANK(Accrual!P38), "", Accrual!P38) | O41: =IF(ISBLANK('Cash Flow'!P38), "",'Cash Flow'!P38) | P41: =IFERROR(IF(O41="", "", O41/K41), 0) | Q41: =IF(K41="", "", K41-O41)
A42: 2.1 | B42: Preliminaries | I42: =IF(H42="", "", J42-H42) | J42: =IF(ISBLANK(Projection!P39), "", Projection!P39) | K42: =IF(ISBLANK('Committed Cost'!P39), "", 'Committed Cost'!P39) | L42: =IFERROR(IF(ISBLANK(F42), "", K42/F42), 0) | M42: =IF(F42="", "", F42-K42) | N42: =IF(ISBLANK(Accrual!P39), "", Accrual!P39) | O42: =IF(ISBLANK('Cash Flow'!P39), "",'Cash Flow'!P39) | P42: =IFERROR(IF(O42="", "", O42/K42), 0) | Q42: =IF(K42="", "", K42-O42)
A43: 2.1.1 | B43: -Manpower (Mgt. & Supervision) | C43: 19623.397 | D43: 29952.64 | E43: 0 | F43: =D43+E43 -> 29952.64 | G43: 80028.454 | H43: 80028.454 | I43: =IF(H43="", "", J43-H43) -> 0 | J43: =IF(ISBLANK(Projection!P40), "", Projection!P40) -> 80028.454 | K43: =IF(ISBLANK('Committed Cost'!P40), "", 'Committed Cost'!P40) -> 79994.223 | L43: =IFERROR(IF(ISBLANK(F43), "", K43/F43), 0) -> 2.6706902 | M43: =IF(F43="", "", F43-K43) -> -50041.583 | N43: =IF(ISBLANK(Accrual!P40), "", Accrual!P40) -> 79994.034 | O43: =IF(ISBLANK('Cash Flow'!P40), "",'Cash Flow'!P40) -> 79994.634 | P43: =IFERROR(IF(O43="", "", O43/K43), 0) -> 1.0000051 | Q43: =IF(K43="", "", K43-O43) -> -0.41179
A44: 2.1.13 | B44: -Manpower (HO-Consultant) | C44: 0 | D44: 0 | E44: 0 | F44: =D44+E44 -> 0 | G44: 25 | H44: 25 | I44: =IF(H44="", "", J44-H44) -> 170 | J44: =IF(ISBLANK(Projection!P41), "", Projection!P41) -> 195 | K44: =IF(ISBLANK('Committed Cost'!P41), "", 'Committed Cost'!P41) -> 191.63963 | L44: =IFERROR(IF(ISBLANK(F44), "", K44/F44), 0) -> 0 | M44: =IF(F44="", "", F44-K44) -> -191.63963 | N44: =IF(ISBLANK(Accrual!P41), "", Accrual!P41) -> 191.63963 | O44: =IF(ISBLANK('Cash Flow'!P41), "",'Cash Flow'!P41) -> 191.27963 | P44: =IFERROR(IF(O44="", "", O44/K44), 0) -> 0.99812147 | Q44: =IF(K44="", "", K44-O44) -> 0.36
A45: 2.1.2 | B45: -Manpower (RE) | C45: 0 | D45: 0 | E45: 0 | F45: =D45+E45 -> 0 | G45: 250 | H45: 250 | I45: =IF(H45="", "", J45-H45) -> 0 | J45: =IF(ISBLANK(Projection!P42), "", Projection!P42) -> 250 | K45: =IF(ISBLANK('Committed Cost'!P42), "", 'Committed Cost'!P42) -> 122.51203 | L45: =IFERROR(IF(ISBLANK(F45), "", K45/F45), 0) -> 0 | M45: =IF(F45="", "", F45-K45) -> -122.51203 | N45: =IF(ISBLANK(Accrual!P42), "", Accrual!P42) -> 122.51203 | O45: =IF(ISBLANK('Cash Flow'!P42), "",'Cash Flow'!P42) -> 122.51203 | P45: =IFERROR(IF(O45="", "", O45/K45), 0) -> 1 | Q45: =IF(K45="", "", K45-O45) -> 0
A46: 2.1.3 | B46: -Manpower (Labour) | C46: 0 | D46: 7622.083 | E46: 0 | F46: =D46+E46 -> 7622.083 | G46: 15643 | H46: 15643 | I46: =IF(H46="", "", J46-H46) -> 0 | J46: =IF(ISBLANK(Projection!P43), "", Projection!P43) -> 15643 | K46: =IF(ISBLANK('Committed Cost'!P43), "", 'Committed Cost'!P43) -> 15420.888 | L46: =IFERROR(IF(ISBLANK(F46), "", K46/F46), 0) -> 2.0231855 | M46: =IF(F46="", "", F46-K46) -> -7798.805 | N46: =IF(ISBLANK(Accrual!P43), "", Accrual!P43) -> 15420.883 | O46: =IF(ISBLANK('Cash Flow'!P43), "",'Cash Flow'!P43) -> 15420.883 | P46: =IFERROR(IF(O46="", "", O46/K46), 0) -> 0.99999968 | Q46: =IF(K46="", "", K46-O46) -> 0.00492
A47: 2.1.4 | B47: -Adm. Cost one off item (Insurance, Bond & Levies) | C47: 1561.889 | D47: 3702.16 | E47: 0 | F47: =D47+E47 -> 3702.16 | G47: 3541 | H47: 3541 | I47: =IF(H47="", "", J47-H47) -> 580 | J47: =IF(ISBLANK(Projection!P44), "", Projection!P44) -> 4121 | K47: =IF(ISBLANK('Committed Cost'!P44), "", 'Committed Cost'!P44) -> 4106.6833 | L47: =IFERROR(IF(ISBLANK(F47), "", K47/F47), 0) -> 1.1092668 | M47: =IF(F47="", "", F47-K47) -> -404.52328 | N47: =IF(ISBLANK(Accrual!P44), "", Accrual!P44) -> 4106.6833 | O47: =IF(ISBLANK('Cash Flow'!P44), "",'Cash Flow'!P44) -> 4108.6133 | P47: =IFERROR(IF(O47="", "", O47/K47), 0) -> 1.00047 | Q47: =IF(K47="", "", K47-O47) -> -1.93
A48: 2.1.5 | B48: -Adm. Cost Others (General site overhead, includes RE) | C48: 7686.756 | D48: 28236.281 | E48: 0 | F48: =D48+E48 -> 28236.281 | G48: 38720 | H48: 38720 | I48: =IF(H48="", "", J48-H48) -> 0 | J48: =IF(ISBLANK(Projection!P45), "", Projection!P45) -> 38720 | K48: =IF(ISBLANK('Committed Cost'!P45), "", 'Committed Cost'!P45) -> 36097.869 | L48: =IFERROR(IF(ISBLANK(F48), "", K48/F48), 0) -> 1.2784215 | M48: =IF(F48="", "", F48-K48) -> -7861.5882 | N48: =IF(ISBLANK(Accrual!P45), "", Accrual!P45) -> 31951.651 | O48: =IF(ISBLANK('Cash Flow'!P45), "",'Cash Flow'!P45) -> 31635.065 | P48: =IFERROR(IF(O48="", "", O48/K48), 0) -> 0.87636932 | Q48: =IF(K48="", "", K48-O48) -> 4462.804
A49: 2.1.6 | B49: -Adm. Cost Financial Cost (TR interest & Bank charge) | C49: 0 | D49: 0 | E49: 0 | F49: =D49+E49 -> 0 | G49: 0 | H49: 0 | I49: =IF(H49="", "", J49-H49) -> 0 | J49: =IF(ISBLANK(Projection!P46), "", Projection!P46) -> 0 | K49: =IF(ISBLANK('Committed Cost'!P46), "", 'Committed Cost'!P46) -> 0 | L49: =IFERROR(IF(ISBLANK(F49), "", K49/F49), 0) -> 0 | M49: =IF(F49="", "", F49-K49) -> 0 | N49: =IF(ISBLANK(Accrual!P46), "", Accrual!P46) -> 0 | O49: =IF(ISBLANK('Cash Flow'!P46), "",'Cash Flow'!P46) -> 0 | P49: =IFERROR(IF(O49="", "", O49/K49), 0) -> 0 | Q49: =IF(K49="", "", K49-O49) -> 0
A50: 2.1.7 | B50: -Adm. Cost Messing | C50: 1252.803 | D50: 4602.007 | E50: 0 | F50: =D50+E50 -> 4602.007 | G50: 2500 | H50: 2500 | I50: =IF(H50="", "", J50-H50) -> 0 | J50: =IF(ISBLANK(Projection!P47), "", Projection!P47) -> 2500 | K50: =IF(ISBLANK('Committed Cost'!P47), "", 'Committed Cost'!P47) -> 2213.6186 | L50: =IFERROR(IF(ISBLANK(F50), "", K50/F50), 0) -> 0.48101157 | M50: =IF(F50="", "", F50-K50) -> 2388.3884 | N50: =IF(ISBLANK(Accrual!P47), "", Accrual!P47) -> 2007.1258 | O50: =IF(ISBLANK('Cash Flow'!P47), "",'Cash Flow'!P47) -> 2001.6898 | P50: =IFERROR(IF(O50="", "", O50/K50), 0) -> 0.90426137 | Q50: =IF(K50="", "", K50-O50) -> 211.92882
A51: 2.1.8 | B51: -DSC | C51: 1245.4 | D51: 2528.73 | E51: 0 | F51: =D51+E51 -> 2528.73 | G51: 8956.305 | H51: 8956.305 | I51: =IF(H51="", "", J51-H51) -> 0 | J51: =IF(ISBLANK(Projection!P48), "", Projection!P48) -> 8956.305 | K51: =IF(ISBLANK('Committed Cost'!P48), "", 'Committed Cost'!P48) -> 8912.4318 | L51: =IFERROR(IF(ISBLANK(F51), "", K51/F51), 0) -> 3.5244695 | M51: =IF(F51="", "", F51-K51) -> -6383.7018 | N51: =IF(ISBLANK(Accrual!P48), "", Accrual!P48) -> 7940.6962 | O51: =IF(ISBLANK('Cash Flow'!P48), "",'Cash Flow'!P48) -> 7847.9462 | P51: =IFERROR(IF(O51="", "", O51/K51), 0) -> 0.88056171 | Q51: =IF(K51="", "", K51-O51) -> 1064.4856
A52: 2.1.9 | B52: -General Material | C52: 0 | D52: 0 | E52: 0 | F52: =D52+E52 -> 0 | G52: 0 | H52: 0 | I52: =IF(H52="", "", J52-H52) -> 0 | J52: =IF(ISBLANK(Projection!P49), "", Projection!P49) -> 0 | K52: =IF(ISBLANK('Committed Cost'!P49), "", 'Committed Cost'!P49) -> 0 | L52: =IFERROR(IF(ISBLANK(F52), "", K52/F52), 0) -> 0 | M52: =IF(F52="", "", F52-K52) -> 0 | N52: =IF(ISBLANK(Accrual!P49), "", Accrual!P49) -> 0 | O52: =IF(ISBLANK('Cash Flow'!P49), "",'Cash Flow'!P49) -> 0 | P52: =IFERROR(IF(O52="", "", O52/K52), 0) -> 0 | Q52: =IF(K52="", "", K52-O52) -> 0
A53: 2.1.10 | B53: -Plant | C53: 1926.021 | D53: 5668.525 | E53: 0 | F53: =D53+E53 -> 5668.525 | G53: 16197 | H53: 16197 | I53: =IF(H53="", "", J53-H53) -> 0 | J53: =IF(ISBLANK(Projection!P50), "", Projection!P50) -> 16197 | K53: =IF(ISBLANK('Committed Cost'!P50), "", 'Committed Cost'!P50) -> 11803.192 | L53: =IFERROR(IF(ISBLANK(F53), "", K53/F53), 0) -> 2.0822333 | M53: =IF(F53="", "", F53-K53) -> -6134.6666 | N53: =IF(ISBLANK(Accrual!P50), "", Accrual!P50) -> 10984.39 | O53: =IF(ISBLANK('Cash Flow'!P50), "",'Cash Flow'!P50) -> 9861.1062 | P53: =IFERROR(IF(O53="", "", O53/K53), 0) -> 0.83546099 | Q53: =IF(K53="", "", K53-O53) -> 1942.0854
A54: 2.1.11 | B54: -JV Partner Management Fee | C54: 0 | D54: 0 | E54: 0 | F54: =D54+E54 -> 0 | G54: 0 | H54: 0 | I54: =IF(H54="", "", J54-H54) -> 0 | J54: =IF(ISBLANK(Projection!P51), "", Projection!P51) -> 0 | K54: =IF(ISBLANK('Committed Cost'!P51), "", 'Committed Cost'!P51) -> 0 | L54: =IFERROR(IF(ISBLANK(F54), "", K54/F54), 0) -> 0 | M54: =IF(F54="", "", F54-K54) -> 0 | N54: =IF(ISBLANK(Accrual!P51), "", Accrual!P51) -> 0 | O54: =IF(ISBLANK('Cash Flow'!P51), "",'Cash Flow'!P51) -> 0 | P54: =IFERROR(IF(O54="", "", O54/K54), 0) -> 0 | Q54: =IF(K54="", "", K54-O54) -> 0
A55: 2.1.12 | B55: -Potential Savings (Preliminaries) | C55: 0 | D55: 0 | E55: 0 | F55: =D55+E55 -> 0 | G55: 0 | H55: 0 | I55: =IF(H55="", "", J55-H55) -> 0 | J55: =IF(ISBLANK(Projection!P52), "", Projection!P52) -> 0 | K55: =IF(ISBLANK('Committed Cost'!P52), "", 'Committed Cost'!P52) -> 0 | L55: =IFERROR(IF(ISBLANK(F55), "", K55/F55), 0) -> 0 | M55: =IF(F55="", "", F55-K55) -> 0 | N55: =IF(ISBLANK(Accrual!P52), "", Accrual!P52) -> 0 | O55: =IF(ISBLANK('Cash Flow'!P52), "",'Cash Flow'!P52) -> 0 | P55: =IFERROR(IF(O55="", "", O55/K55), 0) -> 0 | Q55: =IF(K55="", "", K55-O55) -> 0
A56: 2.2 | B56: Materials | I56: =IF(H56="", "", J56-H56) | J56: =IF(ISBLANK(Projection!P53), "", Projection!P53) | K56: =IF(ISBLANK('Committed Cost'!P53), "", 'Committed Cost'!P53) | L56: =IFERROR(IF(ISBLANK(F56), "", K56/F56), 0) | M56: =IF(F56="", "", F56-K56) | N56: =IF(ISBLANK(Accrual!P53), "", Accrual!P53) | O56: =IF(ISBLANK('Cash Flow'!P53), "",'Cash Flow'!P53) | P56: =IFERROR(IF(O56="", "", O56/K56), 0) | Q56: =IF(K56="", "", K56-O56)
A57: 2.2.1 | B57: -Concrete | C57: 0 | D57: 0 | E57: 0 | F57: =D57+E57 -> 0 | G57: 6350 | H57: 6350 | I57: =IF(H57="", "", J57-H57) -> 1000 | J57: =IF(ISBLANK(Projection!P54), "", Projection!P54) -> 7350 | K57: =IF(ISBLANK('Committed Cost'!P54), "", 'Committed Cost'!P54) -> 7303.688 | L57: =IFERROR(IF(ISBLANK(F57), "", K57/F57), 0) -> 0 | M57: =IF(F57="", "", F57-K57) -> -7303.688 | N57: =IF(ISBLANK(Accrual!P54), "", Accrual!P54) -> 6640.6271 | O57: =IF(ISBLANK('Cash Flow'!P54), "",'Cash Flow'!P54) -> 6243.4321 | P57: =IFERROR(IF(O57="", "", O57/K57), 0) -> 0.85483281 | Q57: =IF(K57="", "", K57-O57) -> 1060.2559
A58: 2.2.2 | B58: -Reinforcement | C58: 0 | D58: 0 | E58: 0 | F58: =D58+E58 -> 0 | G58: 2155 | H58: 2155 | I58: =IF(H58="", "", J58-H58) -> 0 | J58: =IF(ISBLANK(Projection!P55), "", Projection!P55) -> 2155 | K58: =IF(ISBLANK('Committed Cost'!P55), "", 'Committed Cost'!P55) -> 2149.2644 | L58: =IFERROR(IF(ISBLANK(F58), "", K58/F58), 0) -> 0 | M58: =IF(F58="", "", F58-K58) -> -2149.2644 | N58: =IF(ISBLANK(Accrual!P55), "", Accrual!P55) -> 1124.4223 | O58: =IF(ISBLANK('Cash Flow'!P55), "",'Cash Flow'!P55) -> 1124.4223 | P58: =IFERROR(IF(O58="", "", O58/K58), 0) -> 0.52316612 | Q58: =IF(K58="", "", K58-O58) -> 1024.8421
A59: 2.2.3 | B59: -Tile, Granite & Marble | C59: 0 | D59: 0 | E59: 0 | F59: =D59+E59 -> 0 | G59: 0 | H59: 0 | I59: =IF(H59="", "", J59-H59) -> 0 | J59: =IF(ISBLANK(Projection!P56), "", Projection!P56) -> 0 | K59: =IF(ISBLANK('Committed Cost'!P56), "", 'Committed Cost'!P56) -> 0 | L59: =IFERROR(IF(ISBLANK(F59), "", K59/F59), 0) -> 0 | M59: =IF(F59="", "", F59-K59) -> 0 | N59: =IF(ISBLANK(Accrual!P56), "", Accrual!P56) -> 0 | O59: =IF(ISBLANK('Cash Flow'!P56), "",'Cash Flow'!P56) -> 0 | P59: =IFERROR(IF(O59="", "", O59/K59), 0) -> 0 | Q59: =IF(K59="", "", K59-O59) -> 0
A60: 2.2.4 | B60: -Temporary Work (Structural Steel and Sheet Piles) | C60: 0 | D60: 0 | E60: 0 | F60: =D60+E60 -> 0 | G60: 6154 | H60: 6154 | I60: =IF(H60="", "", J60-H60) -> -0.06 | J60: =IF(ISBLANK(Projection!P57), "", Projection!P57) -> 6153.94 | K60: =IF(ISBLANK('Committed Cost'!P57), "", 'Committed Cost'!P57) -> 5995.4202 | L60: =IFERROR(IF(ISBLANK(F60), "", K60/F60), 0) -> 0 | M60: =IF(F60="", "", F60-K60) -> -5995.4202 | N60: =IF(ISBLANK(Accrual!P57), "", Accrual!P57) -> 4951.3909 | O60: =IF(ISBLANK('Cash Flow'!P57), "",'Cash Flow'!P57) -> 4863.1909 | P60: =IFERROR(IF(O60="", "", O60/K60), 0) -> 0.81115096 | Q60: =IF(K60="", "", K60-O60) -> 1132.2294
A61: 2.2.5 | B61: -Structural Steel Member | C61: 0 | D61: 0 | E61: 0 | F61: =D61+E61 -> 0 | G61: 0 | H61: 0 | I61: =IF(H61="", "", J61-H61) -> 0 | J61: =IF(ISBLANK(Projection!P58), "", Projection!P58) -> 0 | K61: =IF(ISBLANK('Committed Cost'!P58), "", 'Committed Cost'!P58) -> 0 | L61: =IFERROR(IF(ISBLANK(F61), "", K61/F61), 0) -> 0 | M61: =IF(F61="", "", F61-K61) -> 0 | N61: =IF(ISBLANK(Accrual!P58), "", Accrual!P58) -> 0 | O61: =IF(ISBLANK('Cash Flow'!P58), "",'Cash Flow'!P58) -> 0 | P61: =IFERROR(IF(O61="", "", O61/K61), 0) -> 0 | Q61: =IF(K61="", "", K61-O61) -> 0
A62: 2.2.6 | B62: -Furniture | C62: 0 | D62: 0 | E62: 0 | F62: =D62+E62 -> 0 | G62: 0 | H62: 0 | I62: =IF(H62="", "", J62-H62) -> 0 | J62: =IF(ISBLANK(Projection!P59), "", Projection!P59) -> 0 | K62: =IF(ISBLANK('Committed Cost'!P59), "", 'Committed Cost'!P59) -> 0 | L62: =IFERROR(IF(ISBLANK(F62), "", K62/F62), 0) -> 0 | M62: =IF(F62="", "", F62-K62) -> 0 | N62: =IF(ISBLANK(Accrual!P59), "", Accrual!P59) -> 0 | O62: =IF(ISBLANK('Cash Flow'!P59), "",'Cash Flow'!P59) -> 0 | P62: =IFERROR(IF(O62="", "", O62/K62), 0) -> 0 | Q62: =IF(K62="", "", K62-O62) -> 0
A63: 2.2.7 | B63: -Sanitary Fitting | C63: 0 | D63: 0 | E63: 0 | F63: =D63+E63 -> 0 | G63: 0 | H63: 0 | I63: =IF(H63="", "", J63-H63) -> 0 | J63: =IF(ISBLANK(Projection!P60), "", Projection!P60) -> 0 | K63: =IF(ISBLANK('Committed Cost'!P60), "", 'Committed Cost'!P60) -> 0 | L63: =IFERROR(IF(ISBLANK(F63), "", K63/F63), 0) -> 0 | M63: =IF(F63="", "", F63-K63) -> 0 | N63: =IF(ISBLANK(Accrual!P60), "", Accrual!P60) -> 0 | O63: =IF(ISBLANK('Cash Flow'!P60), "",'Cash Flow'!P60) -> 0 | P63: =IFERROR(IF(O63="", "", O63/K63), 0) -> 0 | Q63: =IF(K63="", "", K63-O63) -> 0
A64: 2.2.8 | B64: -Ironmongery | C64: 0 | D64: 0 | E64: 0 | F64: =D64+E64 -> 0 | G64: 0 | H64: 0 | I64: =IF(H64="", "", J64-H64) -> 0 | J64: =IF(ISBLANK(Projection!P61), "", Projection!P61) -> 0 | K64: =IF(ISBLANK('Committed Cost'!P61), "", 'Committed Cost'!P61) -> 0 | L64: =IFERROR(IF(ISBLANK(F64), "", K64/F64), 0) -> 0 | M64: =IF(F64="", "", F64-K64) -> 0 | N64: =IF(ISBLANK(Accrual!P61), "", Accrual!P61) -> 0 | O64: =IF(ISBLANK('Cash Flow'!P61), "",'Cash Flow'!P61) -> 0 | P64: =IFERROR(IF(O64="", "", O64/K64), 0) -> 0 | Q64: =IF(K64="", "", K64-O64) -> 0
A65: 2.2.9 | B65: -MVAC | C65: 0 | D65: 0 | E65: 0 | F65: =D65+E65 -> 0 | G65: 0 | H65: 0 | I65: =IF(H65="", "", J65-H65) -> 0 | J65: =IF(ISBLANK(Projection!P62), "", Projection!P62) -> 0 | K65: =IF(ISBLANK('Committed Cost'!P62), "", 'Committed Cost'!P62) -> 0 | L65: =IFERROR(IF(ISBLANK(F65), "", K65/F65), 0) -> 0 | M65: =IF(F65="", "", F65-K65) -> 0 | N65: =IF(ISBLANK(Accrual!P62), "", Accrual!P62) -> 0 | O65: =IF(ISBLANK('Cash Flow'!P62), "",'Cash Flow'!P62) -> 0 | P65: =IFERROR(IF(O65="", "", O65/K65), 0) -> 0 | Q65: =IF(K65="", "", K65-O65) -> 0
A66: 2.2.10 | B66: -Electrical | C66: 0 | D66: 0 | E66: 0 | F66: =D66+E66 -> 0 | G66: 0 | H66: 0 | I66: =IF(H66="", "", J66-H66) -> 0 | J66: =IF(ISBLANK(Projection!P63), "", Projection!P63) -> 0 | K66: =IF(ISBLANK('Committed Cost'!P63), "", 'Committed Cost'!P63) -> 0 | L66: =IFERROR(IF(ISBLANK(F66), "", K66/F66), 0) -> 0 | M66: =IF(F66="", "", F66-K66) -> 0 | N66: =IF(ISBLANK(Accrual!P63), "", Accrual!P63) -> 0 | O66: =IF(ISBLANK('Cash Flow'!P63), "",'Cash Flow'!P63) -> 0 | P66: =IFERROR(IF(O66="", "", O66/K66), 0) -> 0 | Q66: =IF(K66="", "", K66-O66) -> 0
A67: 2.2.11 | B67: -P&D | C67: 0 | D67: 0 | E67: 0 | F67: =D67+E67 -> 0 | G67: 0 | H67: 0 | I67: =IF(H67="", "", J67-H67) -> 0 | J67: =IF(ISBLANK(Projection!P64), "", Projection!P64) -> 0 | K67: =IF(ISBLANK('Committed Cost'!P64), "", 'Committed Cost'!P64) -> 0 | L67: =IFERROR(IF(ISBLANK(F67), "", K67/F67), 0) -> 0 | M67: =IF(F67="", "", F67-K67) -> 0 | N67: =IF(ISBLANK(Accrual!P64), "", Accrual!P64) -> 0 | O67: =IF(ISBLANK('Cash Flow'!P64), "",'Cash Flow'!P64) -> 0 | P67: =IFERROR(IF(O67="", "", O67/K67), 0) -> 0 | Q67: =IF(K67="", "", K67-O67) -> 0
A68: 2.2.12 | B68: -FS | C68: 0 | D68: 0 | E68: 0 | F68: =D68+E68 -> 0 | G68: 0 | H68: 0 | I68: =IF(H68="", "", J68-H68) -> 0 | J68: =IF(ISBLANK(Projection!P65), "", Projection!P65) -> 0 | K68: =IF(ISBLANK('Committed Cost'!P65), "", 'Committed Cost'!P65) -> 0 | L68: =IFERROR(IF(ISBLANK(F68), "", K68/F68), 0) -> 0 | M68: =IF(F68="", "", F68-K68) -> 0 | N68: =IF(ISBLANK(Accrual!P65), "", Accrual!P65) -> 0 | O68: =IF(ISBLANK('Cash Flow'!P65), "",'Cash Flow'!P65) -> 0 | P68: =IFERROR(IF(O68="", "", O68/K68), 0) -> 0 | Q68: =IF(K68="", "", K68-O68) -> 0
... A74: 2.2.18 | B74: -P&D Material (for Tunnel) | C74: 0 | D74: 0 | E74: 0 | F74: =D74+E74 -> 0 | G74: 0 | H74: 0 | I74: =IF(H74="", "", J74-H74) -> 0 | J74: =IF(ISBLANK(Projection!P71), "", Projection!P71) -> 0 | K74: =IF(ISBLANK('Committed Cost'!P71), "", 'Committed Cost'!P71) -> 0 | L74: =IFERROR(IF(ISBLANK(F74), "", K74/F74), 0) -> 0 | M74: =IF(F74="", "", F74-K74) -> 0 | N74: =IF(ISBLANK(Accrual!P71), "", Accrual!P71) -> 0 | O74: =IF(ISBLANK('Cash Flow'!P71), "",'Cash Flow'!P71) -> 0 | P74: =IFERROR(IF(O74="", "", O74/K74), 0) -> 0 | Q74: =IF(K74="", "", K74-O74) -> 0
A75: 2.3 | B75: Plant & Machinery | I75: =IF(H75="", "", J75-H75) | J75: =IF(ISBLANK(Projection!P72), "", Projection!P72) | K75: =IF(ISBLANK('Committed Cost'!P72), "", 'Committed Cost'!P72) | L75: =IFERROR(IF(ISBLANK(F75), "", K75/F75), 0) | M75: =IF(F75="", "", F75-K75) | N75: =IF(ISBLANK(Accrual!P72), "", Accrual!P72) | O75: =IF(ISBLANK('Cash Flow'!P72), "",'Cash Flow'!P72) | P75: =IFERROR(IF(O75="", "", O75/K75), 0) | Q75: =IF(K75="", "", K75-O75)
A76: 2.3.1 | B76: -Plant, Equipments & Tools (purchased) | C76: 0 | D76: 1149 | E76: 0 | F76: =D76+E76 -> 1149 | G76: 6000 | H76: 6000 | I76: =IF(H76="", "", J76-H76) -> 0 | J76: =IF(ISBLANK(Projection!P73), "", Projection!P73) -> 6000 | K76: =IF(ISBLANK('Committed Cost'!P73), "", 'Committed Cost'!P73) -> 5046.279 | L76: =IFERROR(IF(ISBLANK(F76), "", K76/F76), 0) -> 4.3918877 | M76: =IF(F76="", "", F76-K76) -> -3897.279 | N76: =IF(ISBLANK(Accrual!P73), "", Accrual!P73) -> 5046.279 | O76: =IF(ISBLANK('Cash Flow'!P73), "",'Cash Flow'!P73) -> 597.279 | P76: =IFERROR(IF(O76="", "", O76/K76), 0) -> 0.11836028 | Q76: =IF(K76="", "", K76-O76) -> 4449
A77: 2.3.2 | B77: -Plant, Equipments & Tools (external hire) | C77: 3220 | D77: 6777 | E77: 0 | F77: =D77+E77 -> 6777 | G77: 44250 | H77: 44250 | I77: =IF(H77="", "", J77-H77) -> 150 | J77: =IF(ISBLANK(Projection!P74), "", Projection!P74) -> 44400 | K77: =IF(ISBLANK('Committed Cost'!P74), "", 'Committed Cost'!P74) -> 36821.745 | L77: =IFERROR(IF(ISBLANK(F77), "", K77/F77), 0) -> 5.43334 | M77: =IF(F77="", "", F77-K77) -> -30044.745 | N77: =IF(ISBLANK(Accrual!P74), "", Accrual!P74) -> 19882.856 | O77: =IF(ISBLANK('Cash Flow'!P74), "",'Cash Flow'!P74) -> 17926.239 | P77: =IFERROR(IF(O77="", "", O77/K77), 0) -> 0.48683838 | Q77: =IF(K77="", "", K77-O77) -> 18895.507
A78: 2.3.3 | B78: -Diesel & Lubricant | C78: 0 | D78: 189.5 | E78: 0 | F78: =D78+E78 -> 189.5 | G78: 924 | H78: 924 | I78: =IF(H78="", "", J78-H78) -> 2 | J78: =IF(ISBLANK(Projection!P75), "", Projection!P75) -> 926 | K78: =IF(ISBLANK('Committed Cost'!P75), "", 'Committed Cost'!P75) -> 925.04926 | L78: =IFERROR(IF(ISBLANK(F78), "", K78/F78), 0) -> 4.8815264 | M78: =IF(F78="", "", F78-K78) -> -735.54926 | N78: =IF(ISBLANK(Accrual!P75), "", Accrual!P75) -> 917.90673 | O78: =IF(ISBLANK('Cash Flow'!P75), "",'Cash Flow'!P75) -> 914.72673 | P78: =IFERROR(IF(O78="", "", O78/K78), 0) -> 0.9888411 | Q78: =IF(K78="", "", K78-O78) -> 10.32253
A79: 2.3.4 | B79: -Repairing | C79: 0 | D79: 0 | E79: 0 | F79: =D79+E79 -> 0 | G79: 0 | H79: 0 | I79: =IF(H79="", "", J79-H79) -> 0 | J79: =IF(ISBLANK(Projection!P76), "", Projection!P76) -> 0 | K79: =IF(ISBLANK('Committed Cost'!P76), "", 'Committed Cost'!P76) -> 0 | L79: =IFERROR(IF(ISBLANK(F79), "", K79/F79), 0) -> 0 | M79: =IF(F79="", "", F79-K79) -> 0 | N79: =IF(ISBLANK(Accrual!P76), "", Accrual!P76) -> 0 | O79: =IF(ISBLANK('Cash Flow'!P76), "",'Cash Flow'!P76) -> 0 | P79: =IFERROR(IF(O79="", "", O79/K79), 0) -> 0 | Q79: =IF(K79="", "", K79-O79) -> 0
A80: 2.3.5 | B80: -Resale | C80: 0 | D80: 0 | E80: 0 | F80: =D80+E80 -> 0 | G80: 0 | H80: 0 | I80: =IF(H80="", "", J80-H80) -> 0 | J80: =IF(ISBLANK(Projection!P77), "", Projection!P77) -> 0 | K80: =IF(ISBLANK('Committed Cost'!P77), "", 'Committed Cost'!P77) -> 0 | L80: =IFERROR(IF(ISBLANK(F80), "", K80/F80), 0) -> 0 | M80: =IF(F80="", "", F80-K80) -> 0 | N80: =IF(ISBLANK(Accrual!P77), "", Accrual!P77) -> 0 | O80: =IF(ISBLANK('Cash Flow'!P77), "",'Cash Flow'!P77) -> 0 | P80: =IFERROR(IF(O80="", "", O80/K80), 0) -> 0 | Q80: =IF(K80="", "", K80-O80) -> 0
A81: 2.3.6 | B81: -Others Plant & Machinery | C81: 0 | D81: 0 | E81: 0 | F81: =D81+E81 -> 0 | G81: 0 | H81: 0 | I81: =IF(H81="", "", J81-H81) -> 0 | J81: =IF(ISBLANK(Projection!P78), "", Projection!P78) -> 0 | K81: =IF(ISBLANK('Committed Cost'!P78), "", 'Committed Cost'!P78) -> 0 | L81: =IFERROR(IF(ISBLANK(F81), "", K81/F81), 0) -> 0 | M81: =IF(F81="", "", F81-K81) -> 0 | N81: =IF(ISBLANK(Accrual!P78), "", Accrual!P78) -> 0 | O81: =IF(ISBLANK('Cash Flow'!P78), "",'Cash Flow'!P78) -> 0 | P81: =IFERROR(IF(O81="", "", O81/K81), 0) -> 0 | Q81: =IF(K81="", "", K81-O81) -> 0
A82: 2.3.7 | B82: -Depreciation (in Ledger) | C82: 0 | D82: 0 | E82: 0 | F82: =D82+E82 -> 0 | G82: 990 | H82: 990 | I82: =IF(H82="", "", J82-H82) -> 16 | J82: =IF(ISBLANK(Projection!P79), "", Projection!P79) -> 1006 | K82: =IF(ISBLANK('Committed Cost'!P79), "", 'Committed Cost'!P79) -> 1005.0599 | L82: =IFERROR(IF(ISBLANK(F82), "", K82/F82), 0) -> 0 | M82: =IF(F82="", "", F82-K82) -> -1005.0599 | N82: =IF(ISBLANK(Accrual!P79), "", Accrual!P79) -> 1005.0599 | O82: =IF(ISBLANK('Cash Flow'!P79), "",'Cash Flow'!P79) -> 1005.0599 | P82: =IFERROR(IF(O82="", "", O82/K82), 0) -> 1 | Q82: =IF(K82="", "", K82-O82) -> 0
A83: 2.3.8 | B83: -Potential Savings (Plants) | C83: 0 | D83: 0 | E83: 0 | F83: =D83+E83 -> 0 | G83: -24803 | H83: -24803 | I83: =IF(H83="", "", J83-H83) -> -210 | J83: =IF(ISBLANK(Projection!P80), "", Projection!P80) -> -25013 | K83: =IF(ISBLANK('Committed Cost'!P80), "", 'Committed Cost'!P80) -> 0 | L83: =IFERROR(IF(ISBLANK(F83), "", K83/F83), 0) -> 0 | M83: =IF(F83="", "", F83-K83) -> 0 | N83: =IF(ISBLANK(Accrual!P80), "", Accrual!P80) -> 0 | O83: =IF(ISBLANK('Cash Flow'!P80), "",'Cash Flow'!P80) -> 0 | P83: =IFERROR(IF(O83="", "", O83/K83), 0) -> 0 | Q83: =IF(K83="", "", K83-O83) -> 0
A84: 2.3.9 | B84: - Plant, Equipments & Tools (internal hire) | C84: 0 | D84: 0 | E84: 0 | F84: =D84+E84 -> 0 | G84: 0 | H84: 0 | I84: =IF(H84="", "", J84-H84) -> 0 | J84: =IF(ISBLANK(Projection!P81), "", Projection!P81) -> 0 | K84: =IF(ISBLANK('Committed Cost'!P81), "", 'Committed Cost'!P81) -> 0 | L84: =IFERROR(IF(ISBLANK(F84), "", K84/F84), 0) -> 0 | M84: =IF(F84="", "", F84-K84) -> 0 | N84: =IF(ISBLANK(Accrual!P81), "", Accrual!P81) -> 0 | O84: =IF(ISBLANK('Cash Flow'!P81), "",'Cash Flow'!P81) -> 0 | P84: =IFERROR(IF(O84="", "", O84/K84), 0) -> 0 | Q84: =IF(K84="", "", K84-O84) -> 0
A85: 2.4 | B85: Subcontractor | I85: =IF(H85="", "", J85-H85) | J85: =IF(ISBLANK(Projection!P82), "", Projection!P82) | K85: =IF(ISBLANK('Committed Cost'!P82), "", 'Committed Cost'!P82) | L85: =IFERROR(IF(ISBLANK(F85), "", K85/F85), 0) | M85: =IF(F85="", "", F85-K85) | N85: =IF(ISBLANK(Accrual!P82), "", Accrual!P82) | O85: =IF(ISBLANK('Cash Flow'!P82), "",'Cash Flow'!P82) | P85: =IFERROR(IF(O85="", "", O85/K85), 0) | Q85: =IF(K85="", "", K85-O85)
A86: 2.4.1 | B86: -Contract Works | C86: 99817.041 | D86: 101834.53 | E86: 0 | F86: =D86+E86 -> 101834.53 | G86: 190240.71 | H86: 190240.71 | I86: =IF(H86="", "", J86-H86) -> 0 | J86: =IF(ISBLANK(Projection!P83), "", Projection!P83) -> 190240.71 | K86: =IF(ISBLANK('Committed Cost'!P83), "", 'Committed Cost'!P83) -> 180211.93 | L86: =IFERROR(IF(ISBLANK(F86), "", K86/F86), 0) -> 1.7696545 | M86: =IF(F86="", "", F86-K86) -> -78377.407 | N86: =IF(ISBLANK(Accrual!P83), "", Accrual!P83) -> 143859.78 | O86: =IF(ISBLANK('Cash Flow'!P83), "",'Cash Flow'!P83) -> 138399.35 | P86: =IFERROR(IF(O86="", "", O86/K86), 0) -> 0.76798106 | Q86: =IF(K86="", "", K86-O86) -> 41812.582
A87: 2.4.2 | B87: -Variation | C87: 0 | D87: 0 | E87: 0 | F87: =D87+E87 -> 0 | G87: 34000 | H87: 34000 | I87: =IF(H87="", "", J87-H87) -> 7473 | J87: =IF(ISBLANK(Projection!P84), "", Projection!P84) -> 41473 | K87: =IF(ISBLANK('Committed Cost'!P84), "", 'Committed Cost'!P84) -> 41435.48 | L87: =IFERROR(IF(ISBLANK(F87), "", K87/F87), 0) -> 0 | M87: =IF(F87="", "", F87-K87) -> -41435.48 | N87: =IF(ISBLANK(Accrual!P84), "", Accrual!P84) -> 36397.163 | O87: =IF(ISBLANK('Cash Flow'!P84), "",'Cash Flow'!P84) -> 32867.684 | P87: =IFERROR(IF(O87="", "", O87/K87), 0) -> 0.79322562 | Q87: =IF(K87="", "", K87-O87) -> 8567.7958
A88: 2.4.3 | B88: -Claim | C88: 0 | D88: 0 | E88: 0 | F88: =D88+E88 -> 0 | G88: 0 | H88: 0 | I88: =IF(H88="", "", J88-H88) -> 0 | J88: =IF(ISBLANK(Projection!P85), "", Projection!P85) -> 0 | K88: =IF(ISBLANK('Committed Cost'!P85), "", 'Committed Cost'!P85) -> 0 | L88: =IFERROR(IF(ISBLANK(F88), "", K88/F88), 0) -> 0 | M88: =IF(F88="", "", F88-K88) -> 0 | N88: =IF(ISBLANK(Accrual!P85), "", Accrual!P85) -> 0 | O88: =IF(ISBLANK('Cash Flow'!P85), "",'Cash Flow'!P85) -> 0 | P88: =IFERROR(IF(O88="", "", O88/K88), 0) -> 0 | Q88: =IF(K88="", "", K88-O88) -> 0
A89: 2.4.4 | B89: -Contra Charge | C89: 0 | D89: 0 | E89: 0 | F89: =D89+E89 -> 0 | G89: 0 | H89: 0 | I89: =IF(H89="", "", J89-H89) -> 0 | J89: =IF(ISBLANK(Projection!P86), "", Projection!P86) -> 0 | K89: =IF(ISBLANK('Committed Cost'!P86), "", 'Committed Cost'!P86) -> 0 | L89: =IFERROR(IF(ISBLANK(F89), "", K89/F89), 0) -> 0 | M89: =IF(F89="", "", F89-K89) -> 0 | N89: =IF(ISBLANK(Accrual!P86), "", Accrual!P86) -> -278.3088 | O89: =IF(ISBLANK('Cash Flow'!P86), "",'Cash Flow'!P86) -> 1417.0262 | P89: =IFERROR(IF(O89="", "", O89/K89), 0) -> 0 | Q89: =IF(K89="", "", K89-O89) -> -1417.0262
A90: 2.4.5 | B90: -Down Payment | C90: 0 | D90: 0 | E90: 0 | F90: =D90+E90 -> 0 | G90: 0 | H90: 0 | I90: =IF(H90="", "", J90-H90) -> 0 | J90: =IF(ISBLANK(Projection!P87), "", Projection!P87) -> 0 | K90: =IF(ISBLANK('Committed Cost'!P87), "", 'Committed Cost'!P87) -> 0 | L90: =IFERROR(IF(ISBLANK(F90), "", K90/F90), 0) -> 0 | M90: =IF(F90="", "", F90-K90) -> 0 | N90: =IF(ISBLANK(Accrual!P87), "", Accrual!P87) -> 0 | O90: =IF(ISBLANK('Cash Flow'!P87), "",'Cash Flow'!P87) -> 243 | P90: =IFERROR(IF(O90="", "", O90/K90), 0) -> 0 | Q90: =IF(K90="", "", K90-O90) -> -243
A91: 2.4.6 | B91: -Retention | C91: 0 | D91: 0 | E91: 0 | F91: =D91+E91 -> 0 | G91: 0 | H91: 0 | I91: =IF(H91="", "", J91-H91) -> 0 | J91: =IF(ISBLANK(Projection!P88), "", Projection!P88) -> 0 | K91: =IF(ISBLANK('Committed Cost'!P88), "", 'Committed Cost'!P88) -> 0 | L91: =IFERROR(IF(ISBLANK(F91), "", K91/F91), 0) -> 0 | M91: =IF(F91="", "", F91-K91) -> 0 | N91: =IF(ISBLANK(Accrual!P88), "", Accrual!P88) -> 0 | O91: =IF(ISBLANK('Cash Flow'!P88), "",'Cash Flow'!P88) -> -7187.7382 | P91: =IFERROR(IF(O91="", "", O91/K91), 0) -> 0 | Q91: =IF(K91="", "", K91-O91) -> 7187.7382
A92: 2.4.7 | B92: -Potential Savings (DSC) | C92: 0 | D92: 0 | E92: 0 | F92: =D92+E92 -> 0 | G92: -53990 | H92: -53990 | I92: =IF(H92="", "", J92-H92) -> -210 | J92: =IF(ISBLANK(Projection!P89), "", Projection!P89) -> -54200 | K92: =IF(ISBLANK('Committed Cost'!P89), "", 'Committed Cost'!P89) -> 0 | L92: =IFERROR(IF(ISBLANK(F92), "", K92/F92), 0) -> 0 | M92: =IF(F92="", "", F92-K92) -> 0 | N92: =IF(ISBLANK(Accrual!P89), "", Accrual!P89) -> 0 | O92: =IF(ISBLANK('Cash Flow'!P89), "",'Cash Flow'!P89) -> 0 | P92: =IFERROR(IF(O92="", "", O92/K92), 0) -> 0 | Q92: =IF(K92="", "", K92-O92) -> 0
A93: 2.4.8 | B93: -Commercial Settlement | C93: 0 | D93: 0 | E93: 0 | F93: =D93+E93 -> 0 | G93: 0 | H93: 0 | I93: =IF(H93="", "", J93-H93) -> 0 | J93: =IF(ISBLANK(Projection!P90), "", Projection!P90) -> 0 | K93: =IF(ISBLANK('Committed Cost'!P90), "", 'Committed Cost'!P90) -> 0 | L93: =IFERROR(IF(ISBLANK(F93), "", K93/F93), 0) -> 0 | M93: =IF(F93="", "", F93-K93) -> 0 | N93: =IF(ISBLANK(Accrual!P90), "", Accrual!P90) -> 0 | O93: =IF(ISBLANK('Cash Flow'!P90), "",'Cash Flow'!P90) -> 0 | P93: =IFERROR(IF(O93="", "", O93/K93), 0) -> 0 | Q93: =IF(K93="", "", K93-O93) -> 0
A94: 2.4.9 | B94: -Contract Works (for Tunnel) | C94: 0 | D94: 0 | E94: 0 | F94: =D94+E94 -> 0 | G94: 0 | H94: 0 | I94: =IF(H94="", "", J94-H94) -> 0 | J94: =IF(ISBLANK(Projection!P91), "", Projection!P91) -> 0 | K94: =IF(ISBLANK('Committed Cost'!P91), "", 'Committed Cost'!P91) -> 0 | L94: =IFERROR(IF(ISBLANK(F94), "", K94/F94), 0) -> 0 | M94: =IF(F94="", "", F94-K94) -> 0 | N94: =IF(ISBLANK(Accrual!P91), "", Accrual!P91) -> 0 | O94: =IF(ISBLANK('Cash Flow'!P91), "",'Cash Flow'!P91) -> 0 | P94: =IFERROR(IF(O94="", "", O94/K94), 0) -> 0 | Q94: =IF(K94="", "", K94-O94) -> 0
A95: 2.5 | B95: Manpower (Labour) for Works | C95: 0 | D95: 0 | E95: 0 | F95: =D95+E95 -> 0 | G95: 0 | H95: 0 | I95: =IF(H95="", "", J95-H95) -> 0 | J95: =IF(ISBLANK(Projection!P92), "", Projection!P92) -> 0 | K95: =IF(ISBLANK('Committed Cost'!P92), "", 'Committed Cost'!P92) -> 0 | L95: =IFERROR(IF(ISBLANK(F95), "", K95/F95), 0) -> 0 | M95: =IF(F95="", "", F95-K95) -> 0 | N95: =IF(ISBLANK(Accrual!P92), "", Accrual!P92) -> 0 | O95: =IF(ISBLANK('Cash Flow'!P92), "",'Cash Flow'!P92) -> 0 | P95: =IFERROR(IF(O95="", "", O95/K95), 0) -> 0 | Q95: =IF(K95="", "", K95-O95) -> 0
A96: 2.6 | B96: Nominated Package | I96: =IF(H96="", "", J96-H96) | J96: =IF(ISBLANK(Projection!P93), "", Projection!P93) | K96: =IF(ISBLANK('Committed Cost'!P93), "", 'Committed Cost'!P93) | L96: =IFERROR(IF(ISBLANK(F96), "", K96/F96), 0) | M96: =IF(F96="", "", F96-K96) | N96: =IF(ISBLANK(Accrual!P93), "", Accrual!P93) | O96: =IF(ISBLANK('Cash Flow'!P93), "",'Cash Flow'!P93) | P96: =IFERROR(IF(O96="", "", O96/K96), 0) | Q96: =IF(K96="", "", K96-O96)
A97: 2.6.1 | B97: -Nominated Subcontractor | C97: 0 | D97: 0 | E97: 0 | F97: =D97+E97 -> 0 | G97: 0 | H97: 0 | I97: =IF(H97="", "", J97-H97) -> 0 | J97: =IF(ISBLANK(Projection!P94), "", Projection!P94) -> 0 | K97: =IF(ISBLANK('Committed Cost'!P94), "", 'Committed Cost'!P94) -> 0 | L97: =IFERROR(IF(ISBLANK(F97), "", K97/F97), 0) -> 0 | M97: =IF(F97="", "", F97-K97) -> 0 | N97: =IF(ISBLANK(Accrual!P94), "", Accrual!P94) -> 0 | O97: =IF(ISBLANK('Cash Flow'!P94), "",'Cash Flow'!P94) -> 0 | P97: =IFERROR(IF(O97="", "", O97/K97), 0) -> 0 | Q97: =IF(K97="", "", K97-O97) -> 0
A98: 2.6.2 | B98: -Nominated Supplier | C98: 0 | D98: 0 | E98: 0 | F98: =D98+E98 -> 0 | G98: 0 | H98: 0 | I98: =IF(H98="", "", J98-H98) -> 0 | J98: =IF(ISBLANK(Projection!P95), "", Projection!P95) -> 0 | K98: =IF(ISBLANK('Committed Cost'!P95), "", 'Committed Cost'!P95) -> 0 | L98: =IFERROR(IF(ISBLANK(F98), "", K98/F98), 0) -> 0 | M98: =IF(F98="", "", F98-K98) -> 0 | N98: =IF(ISBLANK(Accrual!P95), "", Accrual!P95) -> 0 | O98: =IF(ISBLANK('Cash Flow'!P95), "",'Cash Flow'!P95) -> 0 | P98: =IFERROR(IF(O98="", "", O98/K98), 0) -> 0 | Q98: =IF(K98="", "", K98-O98) -> 0
A99: 2.7 | B99: Allow for Contingencies | C99: 0 | D99: 0 | E99: 0 | F99: =D99+E99 -> 0 | G99: 0 | H99: 0 | I99: =IF(H99="", "", J99-H99) -> 0 | J99: =IF(ISBLANK(Projection!P96), "", Projection!P96) -> 0 | K99: =IF(ISBLANK('Committed Cost'!P96), "", 'Committed Cost'!P96) -> 0 | L99: =IFERROR(IF(ISBLANK(F99), "", K99/F99), 0) -> 0 | M99: =IF(F99="", "", F99-K99) -> 0 | N99: =IF(ISBLANK(Accrual!P96), "", Accrual!P96) -> 0 | O99: =IF(ISBLANK('Cash Flow'!P96), "",'Cash Flow'!P96) -> 0 | P99: =IFERROR(IF(O99="", "", O99/K99), 0) -> 0 | Q99: =IF(K99="", "", K99-O99) -> 0
A100: 2.8 | B100: Allow for Defects Rectification Works | C100: 0 | D100: 0 | E100: 0 | F100: =D100+E100 -> 0 | G100: 0 | H100: 0 | I100: =IF(H100="", "", J100-H100) -> 0 | J100: =IF(ISBLANK(Projection!P97), "", Projection!P97) -> 0 | K100: =IF(ISBLANK('Committed Cost'!P97), "", 'Committed Cost'!P97) -> 0 | L100: =IFERROR(IF(ISBLANK(F100), "", K100/F100), 0) -> 0 | M100: =IF(F100="", "", F100-K100) -> 0 | N100: =IF(ISBLANK(Accrual!P97), "", Accrual!P97) -> 0 | O100: =IF(ISBLANK('Cash Flow'!P97), "",'Cash Flow'!P97) -> 0 | P100: =IFERROR(IF(O100="", "", O100/K100), 0) -> 0 | Q100: =IF(K100="", "", K100-O100) -> 0
A101: 2.9 | B101: Tender Fee | C101: 0 | D101: 0 | E101: 0 | F101: =D101+E101 -> 0 | G101: 0 | H101: 0 | I101: =IF(H101="", "", J101-H101) -> 0 | J101: =IF(ISBLANK(Projection!P98), "", Projection!P98) -> 0 | K101: =IF(ISBLANK('Committed Cost'!P98), "", 'Committed Cost'!P98) -> 0 | L101: =IFERROR(IF(ISBLANK(F101), "", K101/F101), 0) -> 0 | M101: =IF(F101="", "", F101-K101) -> 0 | N101: =IF(ISBLANK(Accrual!P98), "", Accrual!P98) -> 0 | O101: =IF(ISBLANK('Cash Flow'!P98), "",'Cash Flow'!P98) -> 0 | P101: =IFERROR(IF(O101="", "", O101/K101), 0) -> 0 | Q101: =IF(K101="", "", K101-O101) -> 0
A102: 2.10 | B102: Partialing Cost Total | C102: 0 | D102: 0 | E102: 0 | F102: =D102+E102 -> 0 | G102: 0 | H102: 0 | I102: =IF(H102="", "", J102-H102) -> 0 | J102: =IF(ISBLANK(Projection!P99), "", Projection!P99) -> 0 | K102: =IF(ISBLANK('Committed Cost'!P99), "", 'Committed Cost'!P99) -> 0 | L102: =IFERROR(IF(ISBLANK(F102), "", K102/F102), 0) -> 0 | M102: =IF(F102="", "", F102-K102) -> 0 | N102: =IF(ISBLANK(Accrual!P99), "", Accrual!P99) -> 0 | O102: =IF(ISBLANK('Cash Flow'!P99), "",'Cash Flow'!P99) -> 0 | P102: =IFERROR(IF(O102="", "", O102/K102), 0) -> 0 | Q102: =IF(K102="", "", K102-O102) -> 0
A103: 2.11 | B103: Incentive / POR Bonus | I103: =IF(H103="", "", J103-H103) | J103: =IF(ISBLANK(Projection!P100), "", Projection!P100) | K103: =IF(ISBLANK('Committed Cost'!P100), "", 'Committed Cost'!P100) | L103: =IFERROR(IF(ISBLANK(F103), "", K103/F103), 0) | M103: =IF(F103="", "", F103-K103) | N103: =IF(ISBLANK(Accrual!P100), "", Accrual!P100) | O103: =IF(ISBLANK('Cash Flow'!P100), "",'Cash Flow'!P100) | P103: =IFERROR(IF(O103="", "", O103/K103), 0) | Q103: =IF(K103="", "", K103-O103)
A104: 2.11.1 | B104: -Cost saving related bonus | C104: 0 | D104: 0 | E104: 0 | F104: =D104+E104 -> 0 | G104: 0 | H104: 0 | I104: =IF(H104="", "", J104-H104) -> 0 | J104: =IF(ISBLANK(Projection!P101), "", Projection!P101) -> 0 | K104: =IF(ISBLANK('Committed Cost'!P101), "", 'Committed Cost'!P101) -> 0 | L104: =IFERROR(IF(ISBLANK(F104), "", K104/F104), 0) -> 0 | M104: =IF(F104="", "", F104-K104) -> 0 | N104: =IF(ISBLANK(Accrual!P101), "", Accrual!P101) -> 0 | O104: =IF(ISBLANK('Cash Flow'!P101), "",'Cash Flow'!P101) -> 0 | P104: =IFERROR(IF(O104="", "", O104/K104), 0) -> 0 | Q104: =IF(K104="", "", K104-O104) -> 0
A105: 2.11.2 | B105: -Non-cost saving related bonus | C105: 0 | D105: 0 | E105: 0 | F105: =D105+E105 -> 0 | G105: 0 | H105: 0 | I105: =IF(H105="", "", J105-H105) -> 0 | J105: =IF(ISBLANK(Projection!P102), "", Projection!P102) -> 0 | K105: =IF(ISBLANK('Committed Cost'!P102), "", 'Committed Cost'!P102) -> 0 | L105: =IFERROR(IF(ISBLANK(F105), "", K105/F105), 0) -> 0 | M105: =IF(F105="", "", F105-K105) -> 0 | N105: =IF(ISBLANK(Accrual!P102), "", Accrual!P102) -> 0 | O105: =IF(ISBLANK('Cash Flow'!P102), "",'Cash Flow'!P102) -> 0 | P105: =IFERROR(IF(O105="", "", O105/K105), 0) -> 0 | Q105: =IF(K105="", "", K105-O105) -> 0
A106: 2.11.3 | B106: -Cost saving achieved | C106: 0 | D106: 0 | E106: 0 | F106: =D106+E106 -> 0 | G106: 0 | H106: 0 | I106: =IF(H106="", "", J106-H106) -> 0 | J106: =IF(ISBLANK(Projection!P103), "", Projection!P103) -> 0 | K106: =IF(ISBLANK('Committed Cost'!P103), "", 'Committed Cost'!P103) -> 0 | L106: =IFERROR(IF(ISBLANK(F106), "", K106/F106), 0) -> 0 | M106: =IF(F106="", "", F106-K106) -> 0 | N106: =IF(ISBLANK(Accrual!P103), "", Accrual!P103) -> 0 | O106: =IF(ISBLANK('Cash Flow'!P103), "",'Cash Flow'!P103) -> 0 | P106: =IFERROR(IF(O106="", "", O106/K106), 0) -> 0 | Q106: =IF(K106="", "", K106-O106) -> 0
A107: 2.12 | B107: CPR Penalty | C107: 0 | D107: 0 | E107: 0 | F107: =D107+E107 -> 0 | G107: 0 | H107: 0 | I107: =IF(H107="", "", J107-H107) -> 0 | J107: =IF(ISBLANK(Projection!P104), "", Projection!P104) -> 0 | K107: =IF(ISBLANK('Committed Cost'!P104), "", 'Committed Cost'!P104) -> 0 | L107: =IFERROR(IF(ISBLANK(F107), "", K107/F107), 0) -> 0 | M107: =IF(F107="", "", F107-K107) -> 0 | N107: =IF(ISBLANK(Accrual!P104), "", Accrual!P104) -> 0 | O107: =IF(ISBLANK('Cash Flow'!P104), "",'Cash Flow'!P104) -> 0 | P107: =IFERROR(IF(O107="", "", O107/K107), 0) -> 0 | Q107: =IF(K107="", "", K107-O107) -> 0
...

Sheet Projection
A1: Chun Wo Construction & Engineering Company Limited
P2: Print Date: 2026-01-13
A3: Project Code: | B3: 968
A4: Project Name: | B4: Contract No. DC/2018/09 Rehabilitation of Trunk Sewers in Tuen Mun
A5: Report Date: | B5: 2025-12-31
A6: Start Date: | B6: 2018-12-28 | G6: Monthly Financial Report
A7: Complete Date: | B7: 2023-03-31 Time Consumed (%): | C7: =IFERROR((B5-B6)/(LEFT(B7, FIND(REPT(" ", 32), B7))-B6), "") | O7: Confidential
A8: Target Complete Date: | B8: 2023-12-01 Target Completed (%): | C8: =IFERROR((B5-B6)/(LEFT(B8, FIND(REPT(" ", 32), B8))-B6), "")
A11: (HK$'000) | G11: Projection
A12: Item | B12: Trade | C12: Bal B/F | D12: Apr | E12: May | F12: Jun | G12: Jul | H12: Aug | I12: Sep | J12: Oct | K12: Nov | L12: Dec | M12: Jan | N12: Feb | O12: Mar | P12: Total
A13: 1 | B13: Income
A14: 1.1 | B14: Original Contract Works | C14: 205000 | D14: 0 | E14: 0 | F14: 0 | G14: 0 | H14: 0 | I14: 0 | J14: 0 | K14: 0 | L14: 0 | P14: =SUM(C14:O14) -> 205000
A15: 1.2 | B15: V.O. / Compensation Events
A16: 1.2.1 | B16: -V.O. / C.E. | C16: 126723.4 | D16: 0 | E16: 0 | F16: 0 | G16: 0 | H16: 0 | I16: 0 | J16: 0 | K16: 0 | L16: 0 | P16: =SUM(C16:O16) -> 126723.4
A17: 1.2.2 | B17: -Fee of C.E. | C17: 25480.08 | D17: 0 | E17: 0 | F17: 0 | G17: 0 | H17: 0 | I17: 0 | J17: 0 | K17: 0 | L17: 0 | P17: =SUM(C17:O17) -> 25480.08
A18: 1.3 | B18: Provisional Sum | C18: 0 | D18: 0 | E18: 0 | F18: 0 | G18: 0 | H18: 0 | I18: 0 | J18: 0 | K18: 0 | L18: 0 | P18: =SUM(C18:O18) -> 0
A19: 1.4 | B19: Adjustment for Provisional Quantities (remeasurement) and PC Rates | C19: 0 | D19: 0 | E19: 0 | F19: 0 | G19: 0 | H19: 0 | I19: 0 | J19: 0 | K19: 0 | L19: 0 | P19: =SUM(C19:O19) -> 0
A20: 1.5 | B20: NSC | C20: 0 | D20: 0 | E20: 0 | F20: 0 | G20: 0 | H20: 0 | I20: 0 | J20: 0 | K20: 0 | L20: 0 | P20: =SUM(C20:O20) -> 0
A21: 1.6 | B21: Profit & Attendance | C21: 0 | D21: 0 | E21: 0 | F21: 0 | G21: 0 | H21: 0 | I21: 0 | J21: 0 | K21: 0 | L21: 0 | P21: =SUM(C21:O21) -> 0
A22: 1.7 | B22: Claims | C22: 0 | D22: 0 | E22: 0 | F22: 0 | G22: 0 | H22: 0 | I22: 0 | J22: 0 | K22: 0 | L22: 0 | P22: =SUM(C22:O22) -> 0
A23: 1.8 | B23: Price Fluctuation / CPF | C23: 52516.54 | D23: 0 | E23: 0 | F23: 0 | G23: 0 | H23: 0 | I23: 0 | J23: 0 | K23: 0 | L23: 0 | P23: =SUM(C23:O23) -> 52516.54
A24: 1.9 | B24: MPF Reimbursement | C24: 0 | D24: 0 | E24: 0 | F24: 0 | G24: 0 | H24: 0 | I24: 0 | J24: 0 | K24: 0 | L24: 0 | P24: =SUM(C24:O24) -> 0
A25: 1.10 | B25: SA | C25: 0 | D25: 0 | E25: 0 | F25: 0 | G25: 0 | H25: 0 | I25: 0 | J25: 0 | K25: 0 | L25: 0 | P25: =SUM(C25:O25) -> 0
A26: 1.11 | B26: CSD | C26: 0 | D26: 0 | E26: 0 | F26: 0 | G26: 0 | H26: 0 | I26: 0 | J26: 0 | K26: 0 | L26: 0 | P26: =SUM(C26:O26) -> 0
A27: 1.12 | B27: Other Revenue / Pain Gain Sharing
A28: 1.12.1 | B28: -Other Revenue | C28: 3067.819 | D28: 0 | E28: 0 | F28: 0 | G28: 0 | H28: 0 | I28: 0 | J28: 0 | K28: 0 | L28: 0 | P28: =SUM(C28:O28) -> 3067.819
A29: 1.12.2 | B29: -Pain Gain Sharing | C29: 15492.6 | D29: 0 | E29: 0 | F29: 0 | G29: 0 | H29: 0 | I29: 0 | J29: 0 | K29: 0 | L29: 0 | P29: =SUM(C29:O29) -> 15492.6
A30: 1.12.3 | B30: -Stretch Target Income | C30: 0 | D30: 0 | E30: 0 | F30: 0 | G30: 0 | H30: 0 | I30: 0 | J30: 0 | K30: 0 | L30: 0 | P30: =SUM(C30:O30) -> 0
A31: 1.13 | B31: Less :LD | C31: 0 | D31: 0 | E31: 0 | F31: 0 | G31: 0 | H31: 0 | I31: 0 | J31: 0 | K31: 0 | L31: 0 | P31: =SUM(C31:O31) -> 0
A32: 1.14 | B32: Less :Retention Money | C32: 0 | D32: 0 | E32: 0 | F32: 0 | G32: 0 | H32: 0 | I32: 0 | J32: 0 | K32: 0 | L32: 0 | P32: =SUM(C32:O32) -> 0
A33: 1.15 | B33: Less :Retention Money (NSC) | C33: 0 | D33: 0 | E33: 0 | F33: 0 | G33: 0 | H33: 0 | I33: 0 | J33: 0 | K33: 0 | L33: 0 | P33: =SUM(C33:O33) -> 0
A34: 1.16 | B34: Partialing Income Total | C34: 0 | D34: 0 | E34: 0 | F34: 0 | G34: 0 | H34: 0 | I34: 0 | J34: 0 | K34: 0 | L34: 0 | P34: =SUM(C34:O34) -> 0
A35: 1.17 | B35: Advance Payment | C35: 0 | D35: 0 | E35: 0 | F35: 0 | G35: 0 | H35: 0 | I35: 0 | J35: 0 | K35: 0 | L35: 0 | P35: =SUM(C35:O35) -> 0
B36: Total Income | C36: =SUM(C13:C35) -> 428280.44 | D36: =SUM(D13:D35) -> 0 | E36: =SUM(E13:E35) -> 0 | F36: =SUM(F13:F35) -> 0 | G36: =SUM(G13:G35) -> 0 | H36: =SUM(H13:H35) -> 0 | I36: =SUM(I13:I35) -> 0 | J36: =SUM(J13:J35) -> 0 | ... P36: =SUM(P13:P35) -> 428280.44
A38: 2 | B38: Less : Cost
A39: 2.1 | B39: Preliminaries
A40: 2.1.1 | B40: -Manpower (Mgt. & Supervision) | C40: 80028.454 | D40: 0 | E40: 0 | F40: 0 | G40: 0 | H40: 0 | I40: 0 | J40: 0 | K40: 0 | L40: 0 | P40: =SUM(C40:O40) -> 80028.454
A41: 2.1.13 | B41: -Manpower (HO-Consultant) | C41: 25 | D41: 0 | E41: 0 | F41: 0 | G41: 20 | H41: 30 | I41: 30 | J41: 0 | K41: 0 | L41: 90 | P41: =SUM(C41:O41) -> 195
A42: 2.1.2 | B42: -Manpower (RE) | C42: 250 | D42: 0 | E42: 0 | F42: 0 | G42: 0 | H42: 0 | I42: 0 | J42: 0 | K42: 0 | L42: 0 | P42: =SUM(C42:O42) -> 250
A43: 2.1.3 | B43: -Manpower (Labour) | C43: 15643 | D43: 0 | E43: 0 | F43: 0 | G43: 0 | H43: 0 | I43: 0 | J43: 0 | K43: 0 | L43: 0 | P43: =SUM(C43:O43) -> 15643
A44: 2.1.4 | B44: -Adm. Cost one off item (Insurance, Bond & Levies) | C44: 3191 | D44: 300 | E44: 50 | F44: 50 | G44: 0 | H44: 0 | I44: 30 | J44: 500 | K44: 0 | L44: 0 | P44: =SUM(C44:O44) -> 4121
A45: 2.1.5 | B45: -Adm. Cost Others (General site overhead, includes RE) | C45: 38620 | D45: 50 | E45: 50 | F45: 0 | G45: 0 | H45: 0 | I45: 0 | J45: 0 | K45: 0 | L45: 0 | P45: =SUM(C45:O45) -> 38720
A46: 2.1.6 | B46: -Adm. Cost Financial Cost (TR interest & Bank charge) | C46: 0 | D46: 0 | E46: 0 | F46: 0 | G46: 0 | H46: 0 | I46: 0 | J46: 0 | K46: 0 | L46: 0 | P46: =SUM(C46:O46) -> 0
A47: 2.1.7 | B47: -Adm. Cost Messing | C47: 2500 | D47: 0 | E47: 0 | F47: 0 | G47: 0 | H47: 0 | I47: 0 | J47: 0 | K47: 0 | L47: 0 | P47: =SUM(C47:O47) -> 2500
A48: 2.1.8 | B48: -DSC | C48: 8956.305 | D48: 0 | E48: 0 | F48: 0 | G48: 0 | H48: 0 | I48: 0 | J48: 0 | K48: 0 | L48: 0 | P48: =SUM(C48:O48) -> 8956.305
A49: 2.1.9 | B49: -General Material | C49: 0 | D49: 0 | E49: 0 | F49: 0 | G49: 0 | H49: 0 | I49: 0 | J49: 0 | K49: 0 | L49: 0 | P49: =SUM(C49:O49) -> 0
A50: 2.1.10 | B50: -Plant | C50: 16197 | D50: 0 | E50: 0 | F50: 0 | G50: 0 | H50: 0 | I50: 0 | J50: 0 | K50: 0 | L50: 0 | P50: =SUM(C50:O50) -> 16197
A51: 2.1.11 | B51: -JV Partner Management Fee | C51: 0 | D51: 0 | E51: 0 | F51: 0 | G51: 0 | H51: 0 | I51: 0 | J51: 0 | K51: 0 | L51: 0 | P51: =SUM(C51:O51) -> 0
A52: 2.1.12 | B52: -Potential Savings (Preliminaries) | C52: 0 | D52: 0 | E52: 0 | F52: 0 | G52: 0 | H52: 0 | I52: 0 | J52: 0 | K52: 0 | L52: 0 | P52: =SUM(C52:O52) -> 0
A53: 2.2 | B53: Materials
A54: 2.2.1 | B54: -Concrete | C54: 6150 | D54: 200 | E54: 0 | F54: 0 | G54: 0 | H54: 0 | I54: 0 | J54: 1000 | K54: 0 | L54: 0 | P54: =SUM(C54:O54) -> 7350
A55: 2.2.2 | B55: -Reinforcement | C55: 2155 | D55: 0 | E55: 0 | F55: 0 | G55: 0 | H55: 0 | I55: 0 | J55: 0 | K55: 0 | L55: 0 | P55: =SUM(C55:O55) -> 2155
A56: 2.2.3 | B56: -Tile, Granite & Marble | C56: 0 | D56: 0 | E56: 0 | F56: 0 | G56: 0 | H56: 0 | I56: 0 | J56: 0 | K56: 0 | L56: 0 | P56: =SUM(C56:O56) -> 0
A57: 2.2.4 | B57: -Temporary Work (Structural Steel and Sheet Piles) | C57: 6153.94 | D57: 0 | E57: 0 | F57: 0 | G57: 0 | H57: 0 | I57: 0 | J57: 0 | K57: 0 | L57: 0 | P57: =SUM(C57:O57) -> 6153.94
A58: 2.2.5 | B58: -Structural Steel Member | C58: 0 | D58: 0 | E58: 0 | F58: 0 | G58: 0 | H58: 0 | I58: 0 | J58: 0 | K58: 0 | L58: 0 | P58: =SUM(C58:O58) -> 0
A59: 2.2.6 | B59: -Furniture | C59: 0 | D59: 0 | E59: 0 | F59: 0 | G59: 0 | H59: 0 | I59: 0 | J59: 0 | K59: 0 | L59: 0 | P59: =SUM(C59:O59) -> 0
A60: 2.2.7 | B60: -Sanitary Fitting | C60: 0 | D60: 0 | E60: 0 | F60: 0 | G60: 0 | H60: 0 | I60: 0 | J60: 0 | K60: 0 | L60: 0 | P60: =SUM(C60:O60) -> 0
A61: 2.2.8 | B61: -Ironmongery | C61: 0 | D61: 0 | E61: 0 | F61: 0 | G61: 0 | H61: 0 | I61: 0 | J61: 0 | K61: 0 | L61: 0 | P61: =SUM(C61:O61) -> 0
A62: 2.2.9 | B62: -MVAC | C62: 0 | D62: 0 | E62: 0 | F62: 0 | G62: 0 | H62: 0 | I62: 0 | J62: 0 | K62: 0 | L62: 0 | P62: =SUM(C62:O62) -> 0
A63: 2.2.10 | B63: -Electrical | C63: 0 | D63: 0 | E63: 0 | F63: 0 | G63: 0 | H63: 0 | I63: 0 | J63: 0 | K63: 0 | L63: 0 | P63: =SUM(C63:O63) -> 0
A64: 2.2.11 | B64: -P&D | C64: 0 | D64: 0 | E64: 0 | F64: 0 | G64: 0 | H64: 0 | I64: 0 | J64: 0 | K64: 0 | L64: 0 | P64: =SUM(C64:O64) -> 0
A65: 2.2.12 | B65: -FS | C65: 0 | D65: 0 | E65: 0 | F65: 0 | G65: 0 | H65: 0 | I65: 0 | J65: 0 | K65: 0 | L65: 0 | P65: =SUM(C65:O65) -> 0
... A71: 2.2.18 | B71: -P&D Material (for Tunnel) | C71: 0 | D71: 0 | E71: 0 | F71: 0 | G71: 0 | H71: 0 | I71: 0 | J71: 0 | K71: 0 | L71: 0 | P71: =SUM(C71:O71) -> 0
A72: 2.3 | B72: Plant & Machinery
A73: 2.3.1 | B73: -Plant, Equipments & Tools (purchased) | C73: 6000 | D73: 0 | E73: 0 | F73: 0 | G73: 0 | H73: 0 | I73: 0 | J73: 0 | K73: 0 | L73: 0 | P73: =SUM(C73:O73) -> 6000
A74: 2.3.2 | B74: -Plant, Equipments & Tools (external hire) | C74: 44250 | D74: 0 | E74: 0 | F74: 0 | G74: 0 | H74: 150 | I74: 0 | J74: 0 | K74: 0 | L74: 0 | P74: =SUM(C74:O74) -> 44400
A75: 2.3.3 | B75: -Diesel & Lubricant | C75: 904 | D75: 0 | E75: 20 | F75: 0 | G75: 0 | H75: 0 | I75: 1 | J75: 1 | K75: 0 | L75: 0 | P75: =SUM(C75:O75) -> 926
A76: 2.3.4 | B76: -Repairing | C76: 0 | D76: 0 | E76: 0 | F76: 0 | G76: 0 | H76: 0 | I76: 0 | J76: 0 | K76: 0 | L76: 0 | P76: =SUM(C76:O76) -> 0
A77: 2.3.5 | B77: -Resale | C77: 0 | D77: 0 | E77: 0 | F77: 0 | G77: 0 | H77: 0 | I77: 0 | J77: 0 | K77: 0 | L77: 0 | P77: =SUM(C77:O77) -> 0
A78: 2.3.6 | B78: -Others Plant & Machinery | C78: 0 | D78: 0 | E78: 0 | F78: 0 | G78: 0 | H78: 0 | I78: 0 | J78: 0 | K78: 0 | L78: 0 | P78: =SUM(C78:O78) -> 0
A79: 2.3.7 | B79: -Depreciation (in Ledger) | C79: 990 | D79: 0 | E79: 0 | F79: 0 | G79: 0 | H79: 13 | I79: 3 | J79: 0 | K79: 0 | L79: 0 | P79: =SUM(C79:O79) -> 1006
A80: 2.3.8 | B80: -Potential Savings (Plants) | C80: -24783 | D80: 0 | E80: -20 | F80: -50 | G80: 0 | H80: -160 | I80: 0 | J80: 0 | K80: 0 | L80: 0 | P80: =SUM(C80:O80) -> -25013
A81: 2.3.9 | B81: - Plant, Equipments & Tools (internal hire) | C81: 0 | D81: 0 | E81: 0 | F81: 0 | G81: 0 | H81: 0 | I81: 0 | J81: 0 | K81: 0 | L81: 0 | P81: =SUM(C81:O81) -> 0
A82: 2.4 | B82: Subcontractor
A83: 2.4.1 | B83: -Contract Works | C83: 190240.71 | D83: 0 | E83: 0 | F83: 0 | G83: 0 | H83: 0 | I83: 0 | J83: 0 | K83: 0 | L83: 0 | P83: =SUM(C83:O83) -> 190240.71
A84: 2.4.2 | B84: -Variation | C84: 33600 | D84: 0 | E84: 400 | F84: 0 | G84: 0 | H84: 7100 | I84: 223 | J84: 0 | K84: 0 | L84: 150 | P84: =SUM(C84:O84) -> 41473
A85: 2.4.3 | B85: -Claim | C85: 0 | D85: 0 | E85: 0 | F85: 0 | G85: 0 | H85: 0 | I85: 0 | J85: 0 | K85: 0 | L85: 0 | P85: =SUM(C85:O85) -> 0
A86: 2.4.4 | B86: -Contra Charge | C86: 0 | D86: 0 | E86: 0 | F86: 0 | G86: 0 | H86: 0 | I86: 0 | J86: 0 | K86: 0 | L86: 0 | P86: =SUM(C86:O86) -> 0
A87: 2.4.5 | B87: -Down Payment | C87: 0 | D87: 0 | E87: 0 | F87: 0 | G87: 0 | H87: 0 | I87: 0 | J87: 0 | K87: 0 | L87: 0 | P87: =SUM(C87:O87) -> 0
A88: 2.4.6 | B88: -Retention | C88: 0 | D88: 0 | E88: 0 | F88: 0 | G88: 0 | H88: 0 | I88: 0 | J88: 0 | K88: 0 | L88: 0 | P88: =SUM(C88:O88) -> 0
A89: 2.4.7 | B89: -Potential Savings (DSC) | C89: -53590 | D89: 0 | E89: -400 | F89: 0 | G89: 0 | H89: -60 | I89: 0 | J89: 0 | K89: 0 | L89: -150 | P89: =SUM(C89:O89) -> -54200
A90: 2.4.8 | B90: -Commercial Settlement | C90: 0 | D90: 0 | E90: 0 | F90: 0 | G90: 0 | H90: 0 | I90: 0 | J90: 0 | K90: 0 | L90: 0 | P90: =SUM(C90:O90) -> 0
A91: 2.4.9 | B91: -Contract Works (for Tunnel) | C91: 0 | D91: 0 | E91: 0 | F91: 0 | G91: 0 | H91: 0 | I91: 0 | J91: 0 | K91: 0 | L91: 0 | P91: =SUM(C91:O91) -> 0
A92: 2.5 | B92: Manpower (Labour) for Works | C92: 0 | D92: 0 | E92: 0 | F92: 0 | G92: 0 | H92: 0 | I92: 0 | J92: 0 | K92: 0 | L92: 0 | P92: =SUM(C92:O92) -> 0
A93: 2.6 | B93: Nominated Package
A94: 2.6.1 | B94: -Nominated Subcontractor | C94: 0 | D94: 0 | E94: 0 | F94: 0 | G94: 0 | H94: 0 | I94: 0 | J94: 0 | K94: 0 | L94: 0 | P94: =SUM(C94:O94) -> 0
A95: 2.6.2 | B95: -Nominated Supplier | C95: 0 | D95: 0 | E95: 0 | F95: 0 | G95: 0 | H95: 0 | I95: 0 | J95: 0 | K95: 0 | L95: 0 | P95: =SUM(C95:O95) -> 0
A96: 2.7 | B96: Allow for Contingencies | C96: 0 | D96: 0 | E96: 0 | F96: 0 | G96: 0 | H96: 0 | I96: 0 | J96: 0 | K96: 0 | L96: 0 | P96: =SUM(C96:O96) -> 0
A97: 2.8 | B97: Allow for Defects Rectification Works | C97: 0 | D97: 0 | E97: 0 | F97: 0 | G97: 0 | H97: 0 | I97: 0 | J97: 0 | K97: 0 | L97: 0 | P97: =SUM(C97:O97) -> 0
A98: 2.9 | B98: Tender Fee | C98: 0 | D98: 0 | E98: 0 | F98: 0 | G98: 0 | H98: 0 | I98: 0 | J98: 0 | K98: 0 | L98: 0 | P98: =SUM(C98:O98) -> 0
A99: 2.10 | B99: Partialing Cost Total | C99: 0 | D99: 0 | E99: 0 | F99: 0 | G99: 0 | H99: 0 | I99: 0 | J99: 0 | K99: 0 | L99: 0 | P99: =SUM(C99:O99) -> 0
A100: 2.11 | B100: Incentive / POR Bonus
A101: 2.11.1 | B101: -Cost saving related bonus | C101: 0 | D101: 0 | E101: 0 | F101: 0 | G101: 0 | H101: 0 | I101: 0 | J101: 0 | K101: 0 | L101: 0 | P101: =SUM(C101:O101) -> 0
A102: 2.11.2 | B102: -Non-cost saving related bonus | C102: 0 | D102: 0 | E102: 0 | F102: 0 | G102: 0 | H102: 0 | I102: 0 | J102: 0 | K102: 0 | L102: 0 | P102: =SUM(C102:O102) -> 0
A103: 2.11.3 | B103: -Cost saving achieved | C103: 0 | D103: 0 | E103: 0 | F103: 0 | G103: 0 | H103: 0 | I103: 0 | J103: 0 | K103: 0 | L103: 0 | P103: =SUM(C103:O103) -> 0
A104: 2.12 | B104: CPR Penalty | C104: 0 | D104: 0 | E104: 0 | F104: 0 | G104: 0 | H104: 0 | I104: 0 | J104: 0 | K104: 0 | L104: 0 | P104: =SUM(C104:O104) -> 0
A105: 2.13 | B105: HO - Transformation Performance Fee | C105: 0 | D105: 0 | E105: 0 | F105: 0 | G105: 0 | H105: 0 | I105: 0 | J105: 0 | K105: 0 | L105: 0 | P105: =SUM(C105:O105) -> 0
A106: 2.14 | B106: Stretch Target (Cost) | C106: 0 | D106: 0 | E106: 0 | F106: 0 | G106: 0 | H106: 0 | I106: 0 | J106: 0 | K106: 0 | L106: 0 | P106: =SUM(C106:O106) -> 0
B107: Total Cost | C107: =SUM(C38:C106) -> 420291.08 | D107: =SUM(D38:D106) -> 0 | E107: =SUM(E38:E106) -> 0 | F107: =SUM(F38:F106) -> 0 | G107: =SUM(G38:G106) -> 0 | H107: =SUM(H38:H106) -> 7073 | I107: =SUM(I38:I106) -> 287 | J107: =SUM(J38:J106) -> -7360 | ... P107: =SUM(P38:P106) -> 420291.08
A109: 3 | B109: Gross Profit (Item 1.0-2.0) (Financial A/C) | C109: =C36-C107 -> 7989.3538 | D109: =D36-D107 -> 0 | E109: =E36-E107 -> 0 | F109: =F36-F107 -> 0 | G109: =G36-G107 -> 0 | H109: =H36-H107 -> -7073 | I109: =I36-I107 -> -287 | J109: =J36-J107 -> 7360 | ... L109: =L36-L107 -> 0 | P109: =P36-P107 -> 7989.3538
...

Sheet Committed Cost
A1: Chun Wo Construction & Engineering Company Limited
P2: Print Date: 2026-01-13
A3: Project Code: | B3: 968
A4: Project Name: | B4: Contract No. DC/2018/09 Rehabilitation of Trunk Sewers in Tuen Mun
A5: Report Date: | B5: 2025-12-31
A6: Start Date: | B6: 2018-12-28 | G6: Monthly Financial Report
A7: Complete Date: | B7: 2023-03-31 Time Consumed (%): | C7: =IFERROR((B5-B6)/(LEFT(B7, FIND(REPT(" ", 32), B7))-B6), "") | O7: Confidential
A8: Target Complete Date: | B8: 2023-12-01 Target Completed (%): | C8: =IFERROR((B5-B6)/(LEFT(B8, FIND(REPT(" ", 32), B8))-B6), "")
A11: (HK$'000) | G11: Committed Cost
A12: Item | B12: Trade | C12: Bal B/F | D12: Apr | E12: May | F12: Jun | G12: Jul | H12: Aug | I12: Sep | J12: Oct | K12: Nov | L12: Dec | M12: Jan | N12: Feb | O12: Mar | P12: Total
A13: 1 | B13: Income
A14: 1.1 | B14: Original Contract Works | C14: 205000 | D14: 0 | E14: 0 | F14: 0 | G14: 0 | H14: 0 | I14: 0 | J14: 0 | K14: 0 | L14: 0 | P14: =SUM(C14:O14) -> 205000
A15: 1.2 | B15: V.O. / Compensation Events
A16: 1.2.1 | B16: -V.O. / C.E. | C16: 71713.6 | D16: 0 | E16: 0 | F16: 0 | G16: 0 | H16: 0 | I16: 0 | J16: 0 | K16: 0 | L16: 0 | P16: =SUM(C16:O16) -> 71713.6
A17: 1.2.2 | B17: -Fee of C.E. | C17: 14311.16 | D17: 0 | E17: 0 | F17: 0 | G17: 0 | H17: 0 | I17: 0 | J17: 0 | K17: 0 | L17: 0 | P17: =SUM(C17:O17) -> 14311.16
A18: 1.3 | B18: Provisional Sum | C18: 0 | D18: 0 | E18: 0 | F18: 0 | G18: 0 | H18: 0 | I18: 0 | J18: 0 | K18: 0 | L18: 0 | P18: =SUM(C18:O18) -> 0
A19: 1.4 | B19: Adjustment for Provisional Quantities (remeasurement) and PC Rates | C19: 0 | D19: 0 | E19: 0 | F19: 0 | G19: 0 | H19: 0 | I19: 0 | J19: 0 | K19: 0 | L19: 0 | P19: =SUM(C19:O19) -> 0
A20: 1.5 | B20: NSC | C20: 0 | D20: 0 | E20: 0 | F20: 0 | G20: 0 | H20: 0 | I20: 0 | J20: 0 | K20: 0 | L20: 0 | P20: =SUM(C20:O20) -> 0
A21: 1.6 | B21: Profit & Attendance | C21: 0 | D21: 0 | E21: 0 | F21: 0 | G21: 0 | H21: 0 | I21: 0 | J21: 0 | K21: 0 | L21: 0 | P21: =SUM(C21:O21) -> 0
A22: 1.7 | B22: Claims | C22: 0 | D22: 0 | E22: 0 | F22: 0 | G22: 0 | H22: 0 | I22: 0 | J22: 0 | K22: 0 | L22: 0 | P22: =SUM(C22:O22) -> 0
A23: 1.8 | B23: Price Fluctuation / CPF | C23: 52429.896 | D23: 0 | E23: 0 | F23: 0 | G23: 0 | H23: 0 | I23: 0 | J23: 0 | K23: 0 | L23: 0 | P23: =SUM(C23:O23) -> 52429.896
A24: 1.9 | B24: MPF Reimbursement | C24: 0 | D24: 0 | E24: 0 | F24: 0 | G24: 0 | H24: 0 | I24: 0 | J24: 0 | K24: 0 | L24: 0 | P24: =SUM(C24:O24) -> 0
A25: 1.10 | B25: SA | C25: 0 | D25: 0 | E25: 0 | F25: 0 | G25: 0 | H25: 0 | I25: 0 | J25: 0 | K25: 0 | L25: 0 | P25: =SUM(C25:O25) -> 0
A26: 1.11 | B26: CSD | C26: 0 | D26: 0 | E26: 0 | F26: 0 | G26: 0 | H26: 0 | I26: 0 | J26: 0 | K26: 0 | L26: 0 | P26: =SUM(C26:O26) -> 0
A27: 1.12 | B27: Other Revenue / Pain Gain Sharing
A28: 1.12.1 | B28: -Other Revenue | C28: 2966.76 | D28: 0 | E28: 0 | F28: 0 | G28: 0 | H28: 0 | I28: 0 | J28: 0 | K28: 0 | L28: 0 | P28: =SUM(C28:O28) -> 2966.76
A29: 1.12.2 | B29: -Pain Gain Sharing | C29: -48534.786 | D29: 0 | E29: 0 | F29: 0 | G29: 0 | H29: 0 | I29: 0 | J29: 0 | K29: 0 | L29: 0 | P29: =SUM(C29:O29) -> -48534.786
A30: 1.12.3 | B30: -Stretch Target Income | C30: 0 | D30: 0 | E30: 0 | F30: 0 | G30: 0 | H30: 0 | I30: 0 | J30: 0 | K30: 0 | L30: 0 | P30: =SUM(C30:O30) -> 0
A31: 1.13 | B31: Less :LD | C31: 0 | D31: 0 | E31: 0 | F31: 0 | G31: 0 | H31: 0 | I31: 0 | J31: 0 | K31: 0 | L31: 0 | P31: =SUM(C31:O31) -> 0
A32: 1.14 | B32: Less :Retention Money | C32: 0 | D32: 0 | E32: 0 | F32: 0 | G32: 0 | H32: 0 | I32: 0 | J32: 0 | K32: 0 | L32: 0 | P32: =SUM(C32:O32) -> 0
A33: 1.15 | B33: Less :Retention Money (NSC) | C33: 0 | D33: 0 | E33: 0 | F33: 0 | G33: 0 | H33: 0 | I33: 0 | J33: 0 | K33: 0 | L33: 0 | P33: =SUM(C33:O33) -> 0
A34: 1.16 | B34: Partialing Income Total | C34: 0 | D34: 0 | E34: 0 | F34: 0 | G34: 0 | H34: 0 | I34: 0 | J34: 0 | K34: 0 | L34: 0 | P34: =SUM(C34:O34) -> 0
A35: 1.17 | B35: Advance Payment | C35: 0 | D35: 0 | E35: 0 | F35: 0 | G35: 0 | H35: 0 | I35: 0 | J35: 0 | K35: 0 | L35: 0 | P35: =SUM(C35:O35) -> 0
B36: Total Income | C36: =SUM(C13:C35) -> 297886.63 | D36: =SUM(D13:D35) -> 0 | E36: =SUM(E13:E35) -> 0 | F36: =SUM(F13:F35) -> 0 | G36: =SUM(G13:G35) -> 0 | H36: =SUM(H13:H35) -> 0 | I36: =SUM(I13:I35) -> 0 | J36: =SUM(J13:J35) -> 0 | ... P36: =SUM(P13:P35) -> 297886.63
A38: 2 | B38: Less : Cost
A39: 2.1 | B39: Preliminaries
A40: 2.1.1 | B40: -Manpower (Mgt. & Supervision) | C40: 79994.223 | D40: 0 | E40: 0 | F40: 0 | G40: 0 | H40: 0 | I40: 0 | J40: 0 | K40: 0 | L40: 0 | P40: =SUM(C40:O40) -> 79994.223
A41: 2.1.13 | B41: -Manpower (HO-Consultant) | C41: 22.112 | D41: -3 | E41: 3.94 | F41: 0 | G41: 12.69 | H41: 37.34763 | I41: 29.81 | J41: -3.27 | K41: 3.94 | L41: 88.07 | P41: =SUM(C41:O41) -> 191.63963
A42: 2.1.2 | B42: -Manpower (RE) | C42: 122.51203 | D42: 0 | E42: 0 | F42: 0 | G42: 0 | H42: 0 | I42: 0 | J42: 0 | K42: 0 | L42: 0 | P42: =SUM(C42:O42) -> 122.51203
A43: 2.1.3 | B43: -Manpower (Labour) | C43: 15420.888 | D43: 0 | E43: 0 | F43: 0 | G43: 0 | H43: 0 | I43: 0 | J43: 0 | K43: 0 | L43: 0 | P43: =SUM(C43:O43) -> 15420.888
A44: 2.1.4 | B44: -Adm. Cost one off item (Insurance, Bond & Levies) | C44: 3092.8627 | D44: 431.9645 | E44: 47.604 | F44: 46.529 | G44: 0 | H44: 0 | I44: 0 | J44: 46.104 | K44: 441.61909 | L44: 0 | P44: =SUM(C44:O44) -> 4106.6833
A45: 2.1.5 | B45: -Adm. Cost Others (General site overhead, includes RE) | C45: 38610.273 | D45: 42.37786 | E45: 47.103 | F45: 26.51151 | G45: -43.2763 | H45: -66.278 | I45: -2672.6373 | J45: 9.54833 | K45: 136.666 | L45: 7.5809 | P45: =SUM(C45:O45) -> 36097.869
A46: 2.1.6 | B46: -Adm. Cost Financial Cost (TR interest & Bank charge) | C46: 0 | D46: 0 | E46: 0 | F46: 0 | G46: 0 | H46: 0 | I46: 0 | J46: 0 | K46: 0 | L46: 0 | P46: =SUM(C46:O46) -> 0
A47: 2.1.7 | B47: -Adm. Cost Messing | C47: 2213.6186 | D47: 0 | E47: 0 | F47: 0 | G47: 0 | H47: 0 | I47: 0 | J47: 0 | K47: 0 | L47: 0 | P47: =SUM(C47:O47) -> 2213.6186
A48: 2.1.8 | B48: -DSC | C48: 8912.4318 | D48: 0 | E48: 0 | F48: 0 | G48: 0 | H48: 0 | I48: 0 | J48: 0 | K48: 0 | L48: 0 | P48: =SUM(C48:O48) -> 8912.4318
A49: 2.1.9 | B49: -General Material | C49: 0 | D49: 0 | E49: 0 | F49: 0 | G49: 0 | H49: 0 | I49: 0 | J49: 0 | K49: 0 | L49: 0 | P49: =SUM(C49:O49) -> 0
A50: 2.1.10 | B50: -Plant | C50: 16158.192 | D50: 0 | E50: 0 | F50: 0 | G50: 0 | H50: 0 | I50: -4355 | J50: 0 | K50: 0 | L50: 0 | P50: =SUM(C50:O50) -> 11803.192
A51: 2.1.11 | B51: -JV Partner Management Fee | C51: 0 | D51: 0 | E51: 0 | F51: 0 | G51: 0 | H51: 0 | I51: 0 | J51: 0 | K51: 0 | L51: 0 | P51: =SUM(C51:O51) -> 0
A52: 2.1.12 | B52: -Potential Savings (Preliminaries) | C52: 0 | D52: 0 | E52: 0 | F52: 0 | G52: 0 | H52: 0 | I52: 0 | J52: 0 | K52: 0 | L52: 0 | P52: =SUM(C52:O52) -> 0
A53: 2.2 | B53: Materials
A54: 2.2.1 | B54: -Concrete | C54: 6146.0105 | D54: 142.632 | E54: 0 | F54: 60.885 | G54: 0 | H54: 0 | I54: 0 | J54: 0 | K54: 954.1605 | L54: 0 | P54: =SUM(C54:O54) -> 7303.688
A55: 2.2.2 | B55: -Reinforcement | C55: 2149.2644 | D55: 0 | E55: 0 | F55: 0 | G55: 0 | H55: 0 | I55: 0 | J55: 0 | K55: 0 | L55: 0 | P55: =SUM(C55:O55) -> 2149.2644
A56: 2.2.3 | B56: -Tile, Granite & Marble | C56: 0 | D56: 0 | E56: 0 | F56: 0 | G56: 0 | H56: 0 | I56: 0 | J56: 0 | K56: 0 | L56: 0 | P56: =SUM(C56:O56) -> 0
A57: 2.2.4 | B57: -Temporary Work (Structural Steel and Sheet Piles) | C57: 6013.8202 | D57: 0 | E57: 0 | F57: 0 | G57: 0 | H57: 0 | I57: -18.4 | J57: 0 | K57: 0 | L57: 0 | P57: =SUM(C57:O57) -> 5995.4202
A58: 2.2.5 | B58: -Structural Steel Member | C58: 0 | D58: 0 | E58: 0 | F58: 0 | G58: 0 | H58: 0 | I58: 0 | J58: 0 | K58: 0 | L58: 0 | P58: =SUM(C58:O58) -> 0
A59: 2.2.6 | B59: -Furniture | C59: 0 | D59: 0 | E59: 0 | F59: 0 | G59: 0 | H59: 0 | I59: 0 | J59: 0 | K59: 0 | L59: 0 | P59: =SUM(C59:O59) -> 0
A60: 2.2.7 | B60: -Sanitary Fitting | C60: 0 | D60: 0 | E60: 0 | F60: 0 | G60: 0 | H60: 0 | I60: 0 | J60: 0 | K60: 0 | L60: 0 | P60: =SUM(C60:O60) -> 0
A61: 2.2.8 | B61: -Ironmongery | C61: 0 | D61: 0 | E61: 0 | F61: 0 | G61: 0 | H61: 0 | I61: 0 | J61: 0 | K61: 0 | L61: 0 | P61: =SUM(C61:O61) -> 0
A62: 2.2.9 | B62: -MVAC | C62: 0 | D62: 0 | E62: 0 | F62: 0 | G62: 0 | H62: 0 | I62: 0 | J62: 0 | K62: 0 | L62: 0 | P62: =SUM(C62:O62) -> 0
A63: 2.2.10 | B63: -Electrical | C63: 0 | D63: 0 | E63: 0 | F63: 0 | G63: 0 | H63: 0 | I63: 0 | J63: 0 | K63: 0 | L63: 0 | P63: =SUM(C63:O63) -> 0
A64: 2.2.11 | B64: -P&D | C64: 0 | D64: 0 | E64: 0 | F64: 0 | G64: 0 | H64: 0 | I64: 0 | J64: 0 | K64: 0 | L64: 0 | P64: =SUM(C64:O64) -> 0
A65: 2.2.12 | B65: -FS | C65: 0 | D65: 0 | E65: 0 | F65: 0 | G65: 0 | H65: 0 | I65: 0 | J65: 0 | K65: 0 | L65: 0 | P65: =SUM(C65:O65) -> 0
... A71: 2.2.18 | B71: -P&D Material (for Tunnel) | C71: 0 | D71: 0 | E71: 0 | F71: 0 | G71: 0 | H71: 0 | I71: 0 | J71: 0 | K71: 0 | L71: 0 | P71: =SUM(C71:O71) -> 0
A72: 2.3 | B72: Plant & Machinery
A73: 2.3.1 | B73: -Plant, Equipments & Tools (purchased) | C73: 5046.279 | D73: 0 | E73: 0 | F73: 0 | G73: 0 | H73: 0 | I73: 0 | J73: 0 | K73: 0 | L73: 0 | P73: =SUM(C73:O73) -> 5046.279
A74: 2.3.2 | B74: -Plant, Equipments & Tools (external hire) | C74: 43880.211 | D74: 91.3 | E74: 18 | F74: 71.75 | G74: 163.8 | H74: 55.6 | I74: -7463.416 | J74: 0 | K74: 4.5 | L74: 0 | P74: =SUM(C74:O74) -> 36821.745
A75: 2.3.3 | B75: -Diesel & Lubricant | C75: 896.6581 | D75: 6.0984 | E75: 4.2624 | F75: 4.653 | G75: 7.77294 | H75: 0 | I75: 4.02724 | J75: 1.57718 | K75: 0 | L75: 0 | P75: =SUM(C75:O75) -> 925.04926
A76: 2.3.4 | B76: -Repairing | C76: 0 | D76: 0 | E76: 0 | F76: 0 | G76: 0 | H76: 0 | I76: 0 | J76: 0 | K76: 0 | L76: 0 | P76: =SUM(C76:O76) -> 0
A77: 2.3.5 | B77: -Resale | C77: 0 | D77: 0 | E77: 0 | F77: 0 | G77: 0 | H77: 0 | I77: 0 | J77: 0 | K77: 0 | L77: 0 | P77: =SUM(C77:O77) -> 0
A78: 2.3.6 | B78: -Others Plant & Machinery | C78: 0 | D78: 0 | E78: 0 | F78: 0 | G78: 0 | H78: 0 | I78: 0 | J78: 0 | K78: 0 | L78: 0 | P78: =SUM(C78:O78) -> 0
A79: 2.3.7 | B79: -Depreciation (in Ledger) | C79: 985.28575 | D79: 3.84865 | E79: 3.84862 | F79: 3.84864 | G79: 2.74275 | H79: 2.74276 | I79: 2.74275 | J79: 0 | K79: 0 | L79: 0 | P79: =SUM(C79:O79) -> 1005.0599
A80: 2.3.8 | B80: -Potential Savings (Plants) | C80: 0 | D80: 0 | E80: 0 | F80: 0 | G80: 0 | H80: 0 | I80: 0 | J80: 0 | K80: 0 | L80: 0 | P80: =SUM(C80:O80) -> 0
A81: 2.3.9 | B81: - Plant, Equipments & Tools (internal hire) | C81: 0 | D81: 0 | E81: 0 | F81: 0 | G81: 0 | H81: 0 | I81: 0 | J81: 0 | K81: 0 | L81: 0 | P81: =SUM(C81:O81) -> 0
A82: 2.4 | B82: Subcontractor
A83: 2.4.1 | B83: -Contract Works | C83: 180211.93 | D83: 0 | E83: 0 | F83: 0 | G83: 0 | H83: 0 | I83: 0 | J83: 0 | K83: 0 | L83: 0 | P83: =SUM(C83:O83) -> 180211.93
A84: 2.4.2 | B84: -Variation | C84: 41435.48 | D84: 0 | E84: 0 | F84: 0 | G84: 0 | H84: 0 | I84: 0 | J84: 0 | K84: 0 | L84: 0 | P84: =SUM(C84:O84) -> 41435.48
A85: 2.4.3 | B85: -Claim | C85: 0 | D85: 0 | E85: 0 | F85: 0 | G85: 0 | H85: 0 | I85: 0 | J85: 0 | K85: 0 | L85: 0 | P85: =SUM(C85:O85) -> 0
A86: 2.4.4 | B86: -Contra Charge | C86: 0 | D86: 0 | E86: 0 | F86: 0 | G86: 0 | H86: 0 | I86: 0 | J86: 0 | K86: 0 | L86: 0 | P86: =SUM(C86:O86) -> 0
A87: 2.4.5 | B87: -Down Payment | C87: 0 | D87: 0 | E87: 0 | F87: 0 | G87: 0 | H87: 0 | I87: 0 | J87: 0 | K87: 0 | L87: 0 | P87: =SUM(C87:O87) -> 0
A88: 2.4.6 | B88: -Retention | C88: 0 | D88: 0 | E88: 0 | F88: 0 | G88: 0 | H88: 0 | I88: 0 | J88: 0 | K88: 0 | L88: 0 | P88: =SUM(C88:O88) -> 0
A89: 2.4.7 | B89: -Potential Savings (DSC) | C89: 0 | D89: 0 | E89: 0 | F89: 0 | G89: 0 | H89: 0 | I89: 0 | J89: 0 | K89: 0 | L89: 0 | P89: =SUM(C89:O89) -> 0
A90: 2.4.8 | B90: -Commercial Settlement | C90: 0 | D90: 0 | E90: 0 | F90: 0 | G90: 0 | H90: 0 | I90: 0 | J90: 0 | K90: 0 | L90: 0 | P90: =SUM(C90:O90) -> 0
A91: 2.4.9 | B91: -Contract Works (for Tunnel) | C91: 0 | D91: 0 | E91: 0 | F91: 0 | G91: 0 | H91: 0 | I91: 0 | J91: 0 | K91: 0 | L91: 0 | P91: =SUM(C91:O91) -> 0
A92: 2.5 | B92: Manpower (Labour) for Works | C92: 0 | D92: 0 | E92: 0 | F92: 0 | G92: 0 | H92: 0 | I92: 0 | J92: 0 | K92: 0 | L92: 0 | P92: =SUM(C92:O92) -> 0
A93: 2.6 | B93: Nominated Package
A94: 2.6.1 | B94: -Nominated Subcontractor | C94: 0 | D94: 0 | E94: 0 | F94: 0 | G94: 0 | H94: 0 | I94: 0 | J94: 0 | K94: 0 | L94: 0 | P94: =SUM(C94:O94) -> 0
A95: 2.6.2 | B95: -Nominated Supplier | C95: 0 | D95: 0 | E95: 0 | F95: 0 | G95: 0 | H95: 0 | I95: 0 | J95: 0 | K95: 0 | L95: 0 | P95: =SUM(C95:O95) -> 0
A96: 2.7 | B96: Allow for Contingencies | C96: 0 | D96: 0 | E96: 0 | F96: 0 | G96: 0 | H96: 0 | I96: 0 | J96: 0 | K96: 0 | L96: 0 | P96: =SUM(C96:O96) -> 0
A97: 2.8 | B97: Allow for Defects Rectification Works | C97: 0 | D97: 0 | E97: 0 | F97: 0 | G97: 0 | H97: 0 | I97: 0 | J97: 0 | K97: 0 | L97: 0 | P97: =SUM(C97:O97) -> 0
A98: 2.9 | B98: Tender Fee | C98: 0 | D98: 0 | E98: 0 | F98: 0 | G98: 0 | H98: 0 | I98: 0 | J98: 0 | K98: 0 | L98: 0 | P98: =SUM(C98:O98) -> 0
A99: 2.10 | B99: Partialing Cost Total | C99: 0 | D99: 0 | E99: 0 | F99: 0 | G99: 0 | H99: 0 | I99: 0 | J99: 0 | K99: 0 | L99: 0 | P99: =SUM(C99:O99) -> 0
A100: 2.11 | B100: Incentive / POR Bonus
A101: 2.11.1 | B101: -Cost saving related bonus | C101: 0 | D101: 0 | E101: 0 | F101: 0 | G101: 0 | H101: 0 | I101: 0 | J101: 0 | K101: 0 | L101: 0 | P101: =SUM(C101:O101) -> 0
A102: 2.11.2 | B102: -Non-cost saving related bonus | C102: 0 | D102: 0 | E102: 0 | F102: 0 | G102: 0 | H102: 0 | I102: 0 | J102: 0 | K102: 0 | L102: 0 | P102: =SUM(C102:O102) -> 0
A103: 2.11.3 | B103: -Cost saving achieved | C103: 0 | D103: 0 | E103: 0 | F103: 0 | G103: 0 | H103: 0 | I103: 0 | J103: 0 | K103: 0 | L103: 0 | P103: =SUM(C103:O103) -> 0
A104: 2.12 | B104: CPR Penalty | C104: 0 | D104: 0 | E104: 0 | F104: 0 | G104: 0 | H104: 0 | I104: 0 | J104: 0 | K104: 0 | L104: 0 | P104: =SUM(C104:O104) -> 0
A105: 2.13 | B105: HO - Transformation Performance Fee | C105: 0 | D105: 0 | E105: 0 | F105: 0 | G105: 0 | H105: 0 | I105: 0 | J105: 0 | K105: 0 | L105: 0 | P105: =SUM(C105:O105) -> 0
A106: 2.14 | B106: Stretch Target (Cost) | C106: 0 | D106: 0 | E106: 0 | F106: 0 | G106: 0 | H106: 0 | I106: 0 | J106: 0 | K106: 0 | L106: 0 | P106: =SUM(C106:O106) -> 0
B107: Total Cost | C107: =SUM(C38:C106) -> 549675.25 | D107: =SUM(D38:D106) -> 731.98341 | E107: =SUM(E38:E106) -> 124.75802 | F107: =SUM(F38:F106) -> 217.26715 | G107: =SUM(G38:G106) -> 205.42739 | H107: =SUM(H38:H106) -> 29.41239 | I107: =SUM(I38:I106) -> -14797.873 | J107: =SUM(J38:J106) -> 53.95951 | ... P107: =SUM(P38:P106) -> 537876.73
A109: 3 | B109: Gross Profit (Item 1.0-2.0) (Financial A/C) | C109: =C36-C107 -> -251788.62 | D109: =D36-D107 -> -731.98341 | E109: =E36-E107 -> -124.75802 | F109: =F36-F107 -> -217.26715 | G109: =G36-G107 -> -205.42739 | H109: =H36-H107 -> -29.41239 | I109: =I36-I107 -> 14797.873 | J109: =J36-J107 -> -53.95951 | ... L109: =L36-L107 -> -95.6509 | P109: =P36-P107 -> -239990.1
...

Sheet Accrual
A1: Chun Wo Construction & Engineering Company Limited
P2: Print Date: 2026-01-13
A3: Project Code: | B3: 968
A4: Project Name: | B4: Contract No. DC/2018/09 Rehabilitation of Trunk Sewers in Tuen Mun
A5: Report Date: | B5: 2025-12-31
A6: Start Date: | B6: 2018-12-28 | G6: Monthly Financial Report
A7: Complete Date: | B7: 2023-03-31 Time Consumed (%): | C7: =IFERROR((B5-B6)/(LEFT(B7, FIND(REPT(" ", 32), B7))-B6), "") | O7: Confidential
A8: Target Complete Date: | B8: 2023-12-01 Target Completed (%): | C8: =IFERROR((B5-B6)/(LEFT(B8, FIND(REPT(" ", 32), B8))-B6), "")
A11: (HK$'000) | G11: Accrual
A12: Item | B12: Trade | C12: Bal B/F | D12: Apr | E12: May | F12: Jun | G12: Jul | H12: Aug | I12: Sep | J12: Oct | K12: Nov | L12: Dec | M12: Jan | N12: Feb | O12: Mar | P12: Total
A13: 1 | B13: Income
A14: 1.1 | B14: Original Contract Works | C14: 425890.83 | D14: 0 | E14: 0 | F14: 0 | G14: 0 | H14: 0 | I14: 0 | J14: 0 | K14: 0 | L14: 2389 | P14: =SUM(C14:O14) -> 428279.83
A15: 1.2 | B15: V.O. / Compensation Events
A16: 1.2.1 | B16: -V.O. / C.E. | C16: 0 | D16: 0 | E16: 0 | F16: 0 | G16: 0 | H16: 0 | I16: 0 | J16: 0 | K16: 0 | L16: 0 | P16: =SUM(C16:O16) -> 0
A17: 1.2.2 | B17: -Fee of C.E. | C17: 0 | D17: 0 | E17: 0 | F17: 0 | G17: 0 | H17: 0 | I17: 0 | J17: 0 | K17: 0 | L17: 0 | P17: =SUM(C17:O17) -> 0
A18: 1.3 | B18: Provisional Sum | C18: 0 | D18: 0 | E18: 0 | F18: 0 | G18: 0 | H18: 0 | I18: 0 | J18: 0 | K18: 0 | L18: 0 | P18: =SUM(C18:O18) -> 0
A19: 1.4 | B19: Adjustment for Provisional Quantities (remeasurement) and PC Rates | C19: 0 | D19: 0 | E19: 0 | F19: 0 | G19: 0 | H19: 0 | I19: 0 | J19: 0 | K19: 0 | L19: 0 | P19: =SUM(C19:O19) -> 0
A20: 1.5 | B20: NSC | C20: 0 | D20: 0 | E20: 0 | F20: 0 | G20: 0 | H20: 0 | I20: 0 | J20: 0 | K20: 0 | L20: 0 | P20: =SUM(C20:O20) -> 0
A21: 1.6 | B21: Profit & Attendance | C21: 0 | D21: 0 | E21: 0 | F21: 0 | G21: 0 | H21: 0 | I21: 0 | J21: 0 | K21: 0 | L21: 0 | P21: =SUM(C21:O21) -> 0
A22: 1.7 | B22: Claims | C22: 0 | D22: 0 | E22: 0 | F22: 0 | G22: 0 | H22: 0 | I22: 0 | J22: 0 | K22: 0 | L22: 0 | P22: =SUM(C22:O22) -> 0
A23: 1.8 | B23: Price Fluctuation / CPF | C23: 0 | D23: 0 | E23: 0 | F23: 0 | G23: 0 | H23: 0 | I23: 0 | J23: 0 | K23: 0 | L23: 0 | P23: =SUM(C23:O23) -> 0
A24: 1.9 | B24: MPF Reimbursement | C24: 0 | D24: 0 | E24: 0 | F24: 0 | G24: 0 | H24: 0 | I24: 0 | J24: 0 | K24: 0 | L24: 0 | P24: =SUM(C24:O24) -> 0
A25: 1.10 | B25: SA | C25: 0 | D25: 0 | E25: 0 | F25: 0 | G25: 0 | H25: 0 | I25: 0 | J25: 0 | K25: 0 | L25: 0 | P25: =SUM(C25:O25) -> 0
A26: 1.11 | B26: CSD | C26: 0 | D26: 0 | E26: 0 | F26: 0 | G26: 0 | H26: 0 | I26: 0 | J26: 0 | K26: 0 | L26: 0 | P26: =SUM(C26:O26) -> 0
A27: 1.12 | B27: Other Revenue / Pain Gain Sharing
A28: 1.12.1 | B28: -Other Revenue | C28: -0.14 | D28: 0 | E28: 0 | F28: 0 | G28: 0 | H28: 0 | I28: 0 | J28: 0 | K28: 0 | L28: 0 | P28: =SUM(C28:O28) -> -0.14
A29: 1.12.2 | B29: -Pain Gain Sharing | C29: 0.19949 | D29: 0 | E29: 0 | F29: 0 | G29: 0 | H29: 0 | I29: 0 | J29: 0 | K29: 0 | L29: 0 | P29: =SUM(C29:O29) -> 0.19949
A30: 1.12.3 | B30: -Stretch Target Income | C30: 0 | D30: 0 | E30: 0 | F30: 0 | G30: 0 | H30: 0 | I30: 0 | J30: 0 | K30: 0 | L30: 0 | P30: =SUM(C30:O30) -> 0
A31: 1.13 | B31: Less :LD | C31: 0 | D31: 0 | E31: 0 | F31: 0 | G31: 0 | H31: 0 | I31: 0 | J31: 0 | K31: 0 | L31: 0 | P31: =SUM(C31:O31) -> 0
A32: 1.14 | B32: Less :Retention Money | C32: 0 | D32: 0 | E32: 0 | F32: 0 | G32: 0 | H32: 0 | I32: 0 | J32: 0 | K32: 0 | L32: 0 | P32: =SUM(C32:O32) -> 0
A33: 1.15 | B33: Less :Retention Money (NSC) | C33: 0 | D33: 0 | E33: 0 | F33: 0 | G33: 0 | H33: 0 | I33: 0 | J33: 0 | K33: 0 | L33: 0 | P33: =SUM(C33:O33) -> 0
A34: 1.16 | B34: Partialing Income Total | C34: 0 | D34: 0 | E34: 0 | F34: 0 | G34: 0 | H34: 0 | I34: 0 | J34: 0 | K34: 0 | L34: 0 | P34: =SUM(C34:O34) -> 0
A35: 1.17 | B35: Advance Payment | C35: 0 | D35: 0 | E35: 0 | F35: 0 | G35: 0 | H35: 0 | I35: 0 | J35: 0 | K35: 0 | L35: 0 | P35: =SUM(C35:O35) -> 0
B36: Total Income | C36: =SUM(C13:C35) -> 425890.89 | D36: =SUM(D13:D35) -> 0 | E36: =SUM(E13:E35) -> 0 | F36: =SUM(F13:F35) -> 0 | G36: =SUM(G13:G35) -> 0 | H36: =SUM(H13:H35) -> 0 | I36: =SUM(I13:I35) -> 0 | J36: =SUM(J13:J35) -> 0 | ... P36: =SUM(P13:P35) -> 428279.89
A38: 2 | B38: Less : Cost
A39: 2.1 | B39: Preliminaries
A40: 2.1.1 | B40: -Manpower (Mgt. & Supervision) | C40: 79994.034 | D40: 0 | E40: 0 | F40: 0 | G40: 0 | H40: 0 | I40: 0 | J40: 0 | K40: 0 | L40: 0 | P40: =SUM(C40:O40) -> 79994.034
A41: 2.1.13 | B41: -Manpower (HO-Consultant) | C41: 22.112 | D41: -3 | E41: 3.94 | F41: 0 | G41: 12.69 | H41: 37.34763 | I41: 29.81 | J41: -3.27 | K41: 3.94 | L41: 88.07 | P41: =SUM(C41:O41) -> 191.63963
A42: 2.1.2 | B42: -Manpower (RE) | C42: 122.51203 | D42: 0 | E42: 0 | F42: 0 | G42: 0 | H42: 0 | I42: 0 | J42: 0 | K42: 0 | L42: 0 | P42: =SUM(C42:O42) -> 122.51203
A43: 2.1.3 | B43: -Manpower (Labour) | C43: 15420.883 | D43: 0 | E43: 0 | F43: 0 | G43: 0 | H43: 0 | I43: 0 | J43: 0 | K43: 0 | L43: 0 | P43: =SUM(C43:O43) -> 15420.883
A44: 2.1.4 | B44: -Adm. Cost one off item (Insurance, Bond & Levies) | C44: 3092.8627 | D44: 431.9645 | E44: 47.604 | F44: 46.529 | G44: 0 | H44: 0 | I44: 0 | J44: 46.104 | K44: 441.61909 | L44: 0 | P44: =SUM(C44:O44) -> 4106.6833
A45: 2.1.5 | B45: -Adm. Cost Others (General site overhead, includes RE) | C45: 34664.27 | D45: 6.8535 | E45: 16.438 | F45: 26.51151 | G45: -43.2763 | H45: -66.278 | I45: -2672.6373 | J45: 11.40333 | K45: 0.785 | L45: 7.5809 | P45: =SUM(C45:O45) -> 31951.651
A46: 2.1.6 | B46: -Adm. Cost Financial Cost (TR interest & Bank charge) | C46: 0 | D46: 0 | E46: 0 | F46: 0 | G46: 0 | H46: 0 | I46: 0 | J46: 0 | K46: 0 | L46: 0 | P46: =SUM(C46:O46) -> 0
A47: 2.1.7 | B47: -Adm. Cost Messing | C47: 2007.1258 | D47: 0 | E47: 0 | F47: 0 | G47: 0 | H47: 0 | I47: 0 | J47: 0 | K47: 0 | L47: 0 | P47: =SUM(C47:O47) -> 2007.1258
A48: 2.1.8 | B48: -DSC | C48: 7940.6962 | D48: 0 | E48: 0 | F48: 0 | G48: 0 | H48: 0 | I48: 0 | J48: 0 | K48: 0 | L48: 0 | P48: =SUM(C48:O48) -> 7940.6962
A49: 2.1.9 | B49: -General Material | C49: 0 | D49: 0 | E49: 0 | F49: 0 | G49: 0 | H49: 0 | I49: 0 | J49: 0 | K49: 0 | L49: 0 | P49: =SUM(C49:O49) -> 0
A50: 2.1.10 | B50: -Plant | C50: 15145.221 | D50: 2.471 | E50: -1.037 | F50: 5.345 | G50: 0.735 | H50: -63.135 | I50: -4355 | J50: 249.79 | K50: 0 | L50: 0 | P50: =SUM(C50:O50) -> 10984.39
A51: 2.1.11 | B51: -JV Partner Management Fee | C51: 0 | D51: 0 | E51: 0 | F51: 0 | G51: 0 | H51: 0 | I51: 0 | J51: 0 | K51: 0 | L51: 0 | P51: =SUM(C51:O51) -> 0
A52: 2.1.12 | B52: -Potential Savings (Preliminaries) | C52: 0 | D52: 0 | E52: 0 | F52: 0 | G52: 0 | H52: 0 | I52: 0 | J52: 0 | K52: 0 | L52: 0 | P52: =SUM(C52:O52) -> 0
A53: 2.2 | B53: Materials
A54: 2.2.1 | B54: -Concrete | C54: 5482.9496 | D54: 159.6075 | E54: 43.9095 | F54: 0 | G54: 0 | H54: 0 | I54: 0 | J54: 954.1605 | K54: 0 | L54: 0 | P54: =SUM(C54:O54) -> 6640.6271
A55: 2.2.2 | B55: -Reinforcement | C55: 1124.4223 | D55: 0 | E55: 0 | F55: 0 | G55: 0 | H55: 0 | I55: 0 | J55: 0 | K55: 0 | L55: 0 | P55: =SUM(C55:O55) -> 1124.4223
A56: 2.2.3 | B56: -Tile, Granite & Marble | C56: 0 | D56: 0 | E56: 0 | F56: 0 | G56: 0 | H56: 0 | I56: 0 | J56: 0 | K56: 0 | L56: 0 | P56: =SUM(C56:O56) -> 0
A57: 2.2.4 | B57: -Temporary Work (Structural Steel and Sheet Piles) | C57: 4969.7909 | D57: 0 | E57: 0 | F57: 0 | G57: 0 | H57: 0 | I57: -18.4 | J57: 0 | K57: 0 | L57: 0 | P57: =SUM(C57:O57) -> 4951.3909
A58: 2.2.5 | B58: -Structural Steel Member | C58: 0 | D58: 0 | E58: 0 | F58: 0 | G58: 0 | H58: 0 | I58: 0 | J58: 0 | K58: 0 | L58: 0 | P58: =SUM(C58:O58) -> 0
A59: 2.2.6 | B59: -Furniture | C59: 0 | D59: 0 | E59: 0 | F59: 0 | G59: 0 | H59: 0 | I59: 0 | J59: 0 | K59: 0 | L59: 0 | P59: =SUM(C59:O59) -> 0
A60: 2.2.7 | B60: -Sanitary Fitting | C60: 0 | D60: 0 | E60: 0 | F60: 0 | G60: 0 | H60: 0 | I60: 0 | J60: 0 | K60: 0 | L60: 0 | P60: =SUM(C60:O60) -> 0
A61: 2.2.8 | B61: -Ironmongery | C61: 0 | D61: 0 | E61: 0 | F61: 0 | G61: 0 | H61: 0 | I61: 0 | J61: 0 | K61: 0 | L61: 0 | P61: =SUM(C61:O61) -> 0
A62: 2.2.9 | B62: -MVAC | C62: 0 | D62: 0 | E62: 0 | F62: 0 | G62: 0 | H62: 0 | I62: 0 | J62: 0 | K62: 0 | L62: 0 | P62: =SUM(C62:O62) -> 0
A63: 2.2.10 | B63: -Electrical | C63: 0 | D63: 0 | E63: 0 | F63: 0 | G63: 0 | H63: 0 | I63: 0 | J63: 0 | K63: 0 | L63: 0 | P63: =SUM(C63:O63) -> 0
A64: 2.2.11 | B64: -P&D | C64: 0 | D64: 0 | E64: 0 | F64: 0 | G64: 0 | H64: 0 | I64: 0 | J64: 0 | K64: 0 | L64: 0 | P64: =SUM(C64:O64) -> 0
A65: 2.2.12 | B65: -FS | C65: 0 | D65: 0 | E65: 0 | F65: 0 | G65: 0 | H65: 0 | I65: 0 | J65: 0 | K65: 0 | L65: 0 | P65: =SUM(C65:O65) -> 0
... A71: 2.2.18 | B71: -P&D Material (for Tunnel) | C71: 0 | D71: 0 | E71: 0 | F71: 0 | G71: 0 | H71: 0 | I71: 0 | J71: 0 | K71: 0 | L71: 0 | P71: =SUM(C71:O71) -> 0
A72: 2.3 | B72: Plant & Machinery
A73: 2.3.1 | B73: -Plant, Equipments & Tools (purchased) | C73: 5046.279 | D73: 0 | E73: 0 | F73: 0 | G73: 0 | H73: 0 | I73: 0 | J73: 0 | K73: 0 | L73: 0 | P73: =SUM(C73:O73) -> 5046.279
A74: 2.3.2 | B74: -Plant, Equipments & Tools (external hire) | C74: 26452.32 | D74: 238.122 | E74: 344.9 | F74: 27.84 | G74: 296.62 | H74: 10.6 | I74: -7594.666 | J74: 107.1193 | K74: 0 | L74: 0 | P74: =SUM(C74:O74) -> 19882.856
A75: 2.3.3 | B75: -Diesel & Lubricant | C75: 889.51557 | D75: 10.3608 | E75: 4.653 | F75: 0 | G75: 7.77294 | H75: 0 | I75: 0 | J75: 5.60442 | K75: 0 | L75: 0 | P75: =SUM(C75:O75) -> 917.90673
A76: 2.3.4 | B76: -Repairing | C76: 0 | D76: 0 | E76: 0 | F76: 0 | G76: 0 | H76: 0 | I76: 0 | J76: 0 | K76: 0 | L76: 0 | P76: =SUM(C76:O76) -> 0
A77: 2.3.5 | B77: -Resale | C77: 0 | D77: 0 | E77: 0 | F77: 0 | G77: 0 | H77: 0 | I77: 0 | J77: 0 | K77: 0 | L77: 0 | P77: =SUM(C77:O77) -> 0
A78: 2.3.6 | B78: -Others Plant & Machinery | C78: 0 | D78: 0 | E78: 0 | F78: 0 | G78: 0 | H78: 0 | I78: 0 | J78: 0 | K78: 0 | L78: 0 | P78: =SUM(C78:O78) -> 0
A79: 2.3.7 | B79: -Depreciation (in Ledger) | C79: 985.28575 | D79: 3.84865 | E79: 3.84862 | F79: 3.84864 | G79: 2.74275 | H79: 2.74276 | I79: 2.74275 | J79: 0 | K79: 0 | L79: 0 | P79: =SUM(C79:O79) -> 1005.0599
A80: 2.3.8 | B80: -Potential Savings (Plants) | C80: 0 | D80: 0 | E80: 0 | F80: 0 | G80: 0 | H80: 0 | I80: 0 | J80: 0 | K80: 0 | L80: 0 | P80: =SUM(C80:O80) -> 0
A81: 2.3.9 | B81: - Plant, Equipments & Tools (internal hire) | C81: 0 | D81: 0 | E81: 0 | F81: 0 | G81: 0 | H81: 0 | I81: 0 | J81: 0 | K81: 0 | L81: 0 | P81: =SUM(C81:O81) -> 0
A82: 2.4 | B82: Subcontractor
A83: 2.4.1 | B83: -Contract Works | C83: 143484.35 | D83: 0 | E83: 0 | F83: 345.9468 | G83: 0 | H83: 0 | I83: 0 | J83: 0 | K83: 29.48762 | L83: 0 | P83: =SUM(C83:O83) -> 143859.78
A84: 2.4.2 | B84: -Variation | C84: 27185.863 | D84: 772.65629 | E84: 0 | F84: 0 | G84: 0 | H84: 8325.6602 | I84: 0 | J84: 0 | K84: 112.98326 | L84: 0 | P84: =SUM(C84:O84) -> 36397.163
A85: 2.4.3 | B85: -Claim | C85: 0 | D85: 0 | E85: 0 | F85: 0 | G85: 0 | H85: 0 | I85: 0 | J85: 0 | K85: 0 | L85: 0 | P85: =SUM(C85:O85) -> 0
A86: 2.4.4 | B86: -Contra Charge | C86: 727.93072 | D86: -449.77362 | E86: 0 | F86: 0 | G86: 0 | H86: -549.83255 | I86: -6.63335 | J86: 0 | K86: 0 | L86: 0 | P86: =SUM(C86:O86) -> -278.3088
A87: 2.4.5 | B87: -Down Payment | C87: 0 | D87: 0 | E87: 0 | F87: 0 | G87: 0 | H87: 0 | I87: 0 | J87: 0 | K87: 0 | L87: 0 | P87: =SUM(C87:O87) -> 0
A88: 2.4.6 | B88: -Retention | C88: 0 | D88: 0 | E88: 0 | F88: 0 | G88: 0 | H88: 0 | I88: 0 | J88: 0 | K88: 0 | L88: 0 | P88: =SUM(C88:O88) -> 0
A89: 2.4.7 | B89: -Potential Savings (DSC) | C89: 0 | D89: 0 | E89: 0 | F89: 0 | G89: 0 | H89: 0 | I89: 0 | J89: 0 | K89: 0 | L89: 0 | P89: =SUM(C89:O89) -> 0
A90: 2.4.8 | B90: -Commercial Settlement | C90: 0 | D90: 0 | E90: 0 | F90: 0 | G90: 0 | H90: 0 | I90: 0 | J90: 0 | K90: 0 | L90: 0 | P90: =SUM(C90:O90) -> 0
A91: 2.4.9 | B91: -Contract Works (for Tunnel) | C91: 0 | D91: 0 | E91: 0 | F91: 0 | G91: 0 | H91: 0 | I91: 0 | J91: 0 | K91: 0 | L91: 0 | P91: =SUM(C91:O91) -> 0
A92: 2.5 | B92: Manpower (Labour) for Works | C92: 0 | D92: 0 | E92: 0 | F92: 0 | G92: 0 | H92: 0 | I92: 0 | J92: 0 | K92: 0 | L92: 0 | P92: =SUM(C92:O92) -> 0
A93: 2.6 | B93: Nominated Package
A94: 2.6.1 | B94: -Nominated Subcontractor | C94: 0 | D94: 0 | E94: 0 | F94: 0 | G94: 0 | H94: 0 | I94: 0 | J94: 0 | K94: 0 | L94: 0 | P94: =SUM(C94:O94) -> 0
A95: 2.6.2 | B95: -Nominated Supplier | C95: 0 | D95: 0 | E95: 0 | F95: 0 | G95: 0 | H95: 0 | I95: 0 | J95: 0 | K95: 0 | L95: 0 | P95: =SUM(C95:O95) -> 0
A96: 2.7 | B96: Allow for Contingencies | C96: 0 | D96: 0 | E96: 0 | F96: 0 | G96: 0 | H96: 0 | I96: 0 | J96: 0 | K96: 0 | L96: 0 | P96: =SUM(C96:O96) -> 0
A97: 2.8 | B97: Allow for Defects Rectification Works | C97: 0 | D97: 0 | E97: 0 | F97: 0 | G97: 0 | H97: 0 | I97: 0 | J97: 0 | K97: 0 | L97: 0 | P97: =SUM(C97:O97) -> 0
A98: 2.9 | B98: Tender Fee | C98: 0 | D98: 0 | E98: 0 | F98: 0 | G98: 0 | H98: 0 | I98: 0 | J98: 0 | K98: 0 | L98: 0 | P98: =SUM(C98:O98) -> 0
A99: 2.10 | B99: Partialing Cost Total | C99: 0 | D99: 0 | E99: 0 | F99: 0 | G99: 0 | H99: 0 | I99: 0 | J99: 0 | K99: 0 | L99: 0 | P99: =SUM(C99:O99) -> 0
A100: 2.11 | B100: Incentive / POR Bonus
A101: 2.11.1 | B101: -Cost saving related bonus | C101: 0 | D101: 0 | E101: 0 | F101: 0 | G101: 0 | H101: 0 | I101: 0 | J101: 0 | K101: 0 | L101: 0 | P101: =SUM(C101:O101) -> 0
A102: 2.11.2 | B102: -Non-cost saving related bonus | C102: 0 | D102: 0 | E102: 0 | F102: 0 | G102: 0 | H102: 0 | I102: 0 | J102: 0 | K102: 0 | L102: 0 | P102: =SUM(C102:O102) -> 0
A103: 2.11.3 | B103: -Cost saving achieved | C103: 0 | D103: 0 | E103: 0 | F103: 0 | G103: 0 | H103: 0 | I103: 0 | J103: 0 | K103: 0 | L103: 0 | P103: =SUM(C103:O103) -> 0
A104: 2.12 | B104: CPR Penalty | C104: 0 | D104: 0 | E104: 0 | F104: 0 | G104: 0 | H104: 0 | I104: 0 | J104: 0 | K104: 0 | L104: 0 | P104: =SUM(C104:O104) -> 0
A105: 2.13 | B105: HO - Transformation Performance Fee | C105: 0 | D105: 0 | E105: 0 | F105: 0 | G105: 0 | H105: 0 | I105: 0 | J105: 0 | K105: 0 | L105: 0 | P105: =SUM(C105:O105) -> 0
A106: 2.14 | B106: Stretch Target (Cost) | C106: 0 | D106: 0 | E106: 0 | F106: 0 | G106: 0 | H106: 0 | I106: 0 | J106: 0 | K106: 0 | L106: 0 | P106: =SUM(C106:O106) -> 0
B107: Total Cost | C107: =SUM(C38:C106) -> 445634.43 | D107: =SUM(D38:D106) -> 1189.8726 | E107: =SUM(E38:E106) -> 467.34612 | F107: =SUM(F38:F106) -> 517.71895 | G107: =SUM(G38:G106) -> 277.28439 | H107: =SUM(H38:H106) -> 7579.1051 | I107: =SUM(I38:I106) -> -14939.784 | J107: =SUM(J38:J106) -> 1136.9915 | ... P107: =SUM(P38:P106) -> 442547.43
A109: 3 | B109: Gross Profit (Item 1.0-2.0) (Financial A/C) | C109: =C36-C107 -> -19743.541 | D109: =D36-D107 -> -1189.8726 | E109: =E36-E107 -> -467.34612 | F109: =F36-F107 -> -517.71895 | G109: =G36-G107 -> -277.28439 | H109: =H36-H107 -> -7579.1051 | I109: =I36-I107 -> 14939.784 | J109: =J36-J107 -> -1136.9915 | ... L109: =L36-L107 -> 2293.3491 | P109: =P36-P107 -> -14267.542
...

Sheet Cash Flow
A1: Chun Wo Construction & Engineering Company Limited
P2: Print Date: 2026-01-13
A3: Project Code: | B3: 968
A4: Project Name: | B4: Contract No. DC/2018/09 Rehabilitation of Trunk Sewers in Tuen Mun
A5: Report Date: | B5: 2025-12-31
A6: Start Date: | B6: 2018-12-28 | G6: Monthly Financial Report
A7: Complete Date: | B7: 2023-03-31 Time Consumed (%): | C7: =IFERROR((B5-B6)/(LEFT(B7, FIND(REPT(" ", 32), B7))-B6), "") | O7: Confidential
A8: Target Complete Date: | B8: 2023-12-01 Target Completed (%): | C8: =IFERROR((B5-B6)/(LEFT(B8, FIND(REPT(" ", 32), B8))-B6), "")
A11: (HK$'000) | G11: Cash Flow
A12: Item | B12: Trade | C12: Bal B/F | D12: Apr | E12: May | F12: Jun | G12: Jul | H12: Aug | I12: Sep | J12: Oct | K12: Nov | L12: Dec | M12: Jan | N12: Feb | O12: Mar | P12: Total
A13: 1 | B13: Income
A14: 1.1 | B14: Original Contract Works | C14: 427975.16 | D14: 0 | E14: 305 | F14: 0 | G14: 0 | H14: 0 | I14: 0 | J14: 0 | K14: 0 | L14: 0 | P14: =SUM(C14:O14) -> 428280.16
A15: 1.2 | B15: V.O. / Compensation Events
A16: 1.2.1 | B16: -V.O. / C.E. | C16: 0 | D16: 0 | E16: 0 | F16: 0 | G16: 0 | H16: 0 | I16: 0 | J16: 0 | K16: 0 | L16: 0 | P16: =SUM(C16:O16) -> 0
A17: 1.2.2 | B17: -Fee of C.E. | C17: 0 | D17: 0 | E17: 0 | F17: 0 | G17: 0 | H17: 0 | I17: 0 | J17: 0 | K17: 0 | L17: 0 | P17: =SUM(C17:O17) -> 0
A18: 1.3 | B18: Provisional Sum | C18: 0 | D18: 0 | E18: 0 | F18: 0 | G18: 0 | H18: 0 | I18: 0 | J18: 0 | K18: 0 | L18: 0 | P18: =SUM(C18:O18) -> 0
A19: 1.4 | B19: Adjustment for Provisional Quantities (remeasurement) and PC Rates | C19: 0 | D19: 0 | E19: 0 | F19: 0 | G19: 0 | H19: 0 | I19: 0 | J19: 0 | K19: 0 | L19: 0 | P19: =SUM(C19:O19) -> 0
A20: 1.5 | B20: NSC | C20: 0 | D20: 0 | E20: 0 | F20: 0 | G20: 0 | H20: 0 | I20: 0 | J20: 0 | K20: 0 | L20: 0 | P20: =SUM(C20:O20) -> 0
A21: 1.6 | B21: Profit & Attendance | C21: 0 | D21: 0 | E21: 0 | F21: 0 | G21: 0 | H21: 0 | I21: 0 | J21: 0 | K21: 0 | L21: 0 | P21: =SUM(C21:O21) -> 0
A22: 1.7 | B22: Claims | C22: 0 | D22: 0 | E22: 0 | F22: 0 | G22: 0 | H22: 0 | I22: 0 | J22: 0 | K22: 0 | L22: 0 | P22: =SUM(C22:O22) -> 0
A23: 1.8 | B23: Price Fluctuation / CPF | C23: 0 | D23: 0 | E23: 0 | F23: 0 | G23: 0 | H23: 0 | I23: 0 | J23: 0 | K23: 0 | L23: 0 | P23: =SUM(C23:O23) -> 0
A24: 1.9 | B24: MPF Reimbursement | C24: 0 | D24: 0 | E24: 0 | F24: 0 | G24: 0 | H24: 0 | I24: 0 | J24: 0 | K24: 0 | L24: 0 | P24: =SUM(C24:O24) -> 0
A25: 1.10 | B25: SA | C25: 0.008 | D25: 0 | E25: 0 | F25: 0 | G25: 0 | H25: 0 | I25: 0 | J25: 0 | K25: 0 | L25: 0 | P25: =SUM(C25:O25) -> 0.008
A26: 1.11 | B26: CSD | C26: 0 | D26: 0 | E26: 0 | F26: 0 | G26: 0 | H26: 0 | I26: 0 | J26: 0 | K26: 0 | L26: 0 | P26: =SUM(C26:O26) -> 0
A27: 1.12 | B27: Other Revenue / Pain Gain Sharing
A28: 1.12.1 | B28: -Other Revenue | C28: 2223.962 | D28: 0 | E28: -2224 | F28: 0 | G28: 0 | H28: 0 | I28: 0 | J28: 0 | K28: 0 | L28: 0 | P28: =SUM(C28:O28) -> -0.038
A29: 1.12.2 | B29: -Pain Gain Sharing | C29: -1980.2005 | D29: 0 | E29: 1980 | F29: 0 | G29: 0 | H29: 0 | I29: 0 | J29: 0 | K29: 0 | L29: 0 | P29: =SUM(C29:O29) -> -0.20051
A30: 1.12.3 | B30: -Stretch Target Income | C30: 0 | D30: 0 | E30: 0 | F30: 0 | G30: 0 | H30: 0 | I30: 0 | J30: 0 | K30: 0 | L30: 0 | P30: =SUM(C30:O30) -> 0
A31: 1.13 | B31: Less :LD | C31: 0 | D31: 0 | E31: 0 | F31: 0 | G31: 0 | H31: 0 | I31: 0 | J31: 0 | K31: 0 | L31: 0 | P31: =SUM(C31:O31) -> 0
A32: 1.14 | B32: Less :Retention Money | C32: -2328.2479 | D32: 0 | E32: -61 | F32: 0 | G32: 0 | H32: 0 | I32: 0 | J32: 0 | K32: 0 | L32: 2389 | P32: =SUM(C32:O32) -> -0.24791
A33: 1.15 | B33: Less :Retention Money (NSC) | C33: 0 | D33: 0 | E33: 0 | F33: 0 | G33: 0 | H33: 0 | I33: 0 | J33: 0 | K33: 0 | L33: 0 | P33: =SUM(C33:O33) -> 0
A34: 1.16 | B34: Partialing Income Total | C34: 0 | D34: 0 | E34: 0 | F34: 0 | G34: 0 | H34: 0 | I34: 0 | J34: 0 | K34: 0 | L34: 0 | P34: =SUM(C34:O34) -> 0
A35: 1.17 | B35: Advance Payment | C35: 0 | D35: 0 | E35: 0 | F35: 0 | G35: 0 | H35: 0 | I35: 0 | J35: 0 | K35: 0 | L35: 0 | P35: =SUM(C35:O35) -> 0
B36: Total Income | C36: =SUM(C13:C35) -> 425890.69 | D36: =SUM(D13:D35) -> 0 | E36: =SUM(E13:E35) -> 0 | F36: =SUM(F13:F35) -> 0 | G36: =SUM(G13:G35) -> 0 | H36: =SUM(H13:H35) -> 0 | I36: =SUM(I13:I35) -> 0 | J36: =SUM(J13:J35) -> 0 | ... P36: =SUM(P13:P35) -> 428279.69
A38: 2 | B38: Less : Cost
A39: 2.1 | B39: Preliminaries
A40: 2.1.1 | B40: -Manpower (Mgt. & Supervision) | C40: 79994.634 | D40: 0 | E40: 0 | F40: 0 | G40: 0 | H40: 0 | I40: 0 | J40: 0 | K40: 0 | L40: 0 | P40: =SUM(C40:O40) -> 79994.634
A41: 2.1.13 | B41: -Manpower (HO-Consultant) | C41: 21.752 | D41: -3 | E41: 3.94 | F41: 0 | G41: 12.69 | H41: 37.34763 | I41: 29.81 | J41: -3.27 | K41: 3.94 | L41: 88.07 | P41: =SUM(C41:O41) -> 191.27963
A42: 2.1.2 | B42: -Manpower (RE) | C42: 122.51203 | D42: 0 | E42: 0 | F42: 0 | G42: 0 | H42: 0 | I42: 0 | J42: 0 | K42: 0 | L42: 0 | P42: =SUM(C42:O42) -> 122.51203
A43: 2.1.3 | B43: -Manpower (Labour) | C43: 15420.883 | D43: 0 | E43: 0 | F43: 0 | G43: 0 | H43: 0 | I43: 0 | J43: 0 | K43: 0 | L43: 0 | P43: =SUM(C43:O43) -> 15420.883
A44: 2.1.4 | B44: -Adm. Cost one off item (Insurance, Bond & Levies) | C44: 3065.4097 | D44: 0 | E44: 1.5 | F44: 29.808 | G44: 478.0685 | H44: 0 | I44: 0 | J44: 46.104 | K44: 441.61909 | L44: 46.104 | P44: =SUM(C44:O44) -> 4108.6133
A45: 2.1.5 | B45: -Adm. Cost Others (General site overhead, includes RE) | C45: 34220.174 | D45: 23.26692 | E45: 57.78874 | F45: 24.51952 | G45: -11.3968 | H45: -48.07709 | I45: -2672.6373 | J45: 4.59933 | K45: 35.98 | L45: 0.848 | P45: =SUM(C45:O45) -> 31635.065
A46: 2.1.6 | B46: -Adm. Cost Financial Cost (TR interest & Bank charge) | C46: 0 | D46: 0 | E46: 0 | F46: 0 | G46: 0 | H46: 0 | I46: 0 | J46: 0 | K46: 0 | L46: 0 | P46: =SUM(C46:O46) -> 0
A47: 2.1.7 | B47: -Adm. Cost Messing | C47: 2001.6898 | D47: 0 | E47: 0 | F47: 0 | G47: 0 | H47: 0 | I47: 0 | J47: 0 | K47: 0 | L47: 0 | P47: =SUM(C47:O47) -> 2001.6898
A48: 2.1.8 | B48: -DSC | C48: 7847.9462 | D48: 0 | E48: 0 | F48: 0 | G48: 0 | H48: 0 | I48: 0 | J48: 0 | K48: 0 | L48: 0 | P48: =SUM(C48:O48) -> 7847.9462
A49: 2.1.9 | B49: -General Material | C49: 0 | D49: 0 | E49: 0 | F49: 0 | G49: 0 | H49: 0 | I49: 0 | J49: 0 | K49: 0 | L49: 0 | P49: =SUM(C49:O49) -> 0
A50: 2.1.10 | B50: -Plant | C50: 13771.052 | D50: 3.66 | E50: 13.169 | F50: 51.125 | G50: 52.64 | H50: 71.15 | I50: -4352.215 | J50: 250.525 | K50: 0 | L50: 0 | P50: =SUM(C50:O50) -> 9861.1062
A51: 2.1.11 | B51: -JV Partner Management Fee | C51: 0 | D51: 0 | E51: 0 | F51: 0 | G51: 0 | H51: 0 | I51: 0 | J51: 0 | K51: 0 | L51: 0 | P51: =SUM(C51:O51) -> 0
A52: 2.1.12 | B52: -Potential Savings (Preliminaries) | C52: 0 | D52: 0 | E52: 0 | F52: 0 | G52: 0 | H52: 0 | I52: 0 | J52: 0 | K52: 0 | L52: 0 | P52: =SUM(C52:O52) -> 0
A53: 2.2 | B53: Materials
A54: 2.2.1 | B54: -Concrete | C54: 5395.3157 | D54: 0 | E54: 142.632 | F54: 57.4779 | G54: 60.885 | H54: 0 | I54: 0 | J54: 0 | K54: 0 | L54: 587.1215 | P54: =SUM(C54:O54) -> 6243.4321
A55: 2.2.2 | B55: -Reinforcement | C55: 1081.1319 | D55: 0 | E55: 43.2904 | F55: 0 | G55: 0 | H55: 0 | I55: 0 | J55: 0 | K55: 0 | L55: 0 | P55: =SUM(C55:O55) -> 1124.4223
A56: 2.2.3 | B56: -Tile, Granite & Marble | C56: 0 | D56: 0 | E56: 0 | F56: 0 | G56: 0 | H56: 0 | I56: 0 | J56: 0 | K56: 0 | L56: 0 | P56: =SUM(C56:O56) -> 0
A57: 2.2.4 | B57: -Temporary Work (Structural Steel and Sheet Piles) | C57: 4862.8309 | D57: 0 | E57: 0 | F57: 18.76 | G57: 0 | H57: 0 | I57: -18.4 | J57: 0 | K57: 0 | L57: 0 | P57: =SUM(C57:O57) -> 4863.1909
A58: 2.2.5 | B58: -Structural Steel Member | C58: 0 | D58: 0 | E58: 0 | F58: 0 | G58: 0 | H58: 0 | I58: 0 | J58: 0 | K58: 0 | L58: 0 | P58: =SUM(C58:O58) -> 0
A59: 2.2.6 | B59: -Furniture | C59: 0 | D59: 0 | E59: 0 | F59: 0 | G59: 0 | H59: 0 | I59: 0 | J59: 0 | K59: 0 | L59: 0 | P59: =SUM(C59:O59) -> 0
A60: 2.2.7 | B60: -Sanitary Fitting | C60: 0 | D60: 0 | E60: 0 | F60: 0 | G60: 0 | H60: 0 | I60: 0 | J60: 0 | K60: 0 | L60: 0 | P60: =SUM(C60:O60) -> 0
A61: 2.2.8 | B61: -Ironmongery | C61: 0 | D61: 0 | E61: 0 | F61: 0 | G61: 0 | H61: 0 | I61: 0 | J61: 0 | K61: 0 | L61: 0 | P61: =SUM(C61:O61) -> 0
A62: 2.2.9 | B62: -MVAC | C62: 0 | D62: 0 | E62: 0 | F62: 0 | G62: 0 | H62: 0 | I62: 0 | J62: 0 | K62: 0 | L62: 0 | P62: =SUM(C62:O62) -> 0
A63: 2.2.10 | B63: -Electrical | C63: 0 | D63: 0 | E63: 0 | F63: 0 | G63: 0 | H63: 0 | I63: 0 | J63: 0 | K63: 0 | L63: 0 | P63: =SUM(C63:O63) -> 0
A64: 2.2.11 | B64: -P&D | C64: 0 | D64: 0 | E64: 0 | F64: 0 | G64: 0 | H64: 0 | I64: 0 | J64: 0 | K64: 0 | L64: 0 | P64: =SUM(C64:O64) -> 0
A65: 2.2.12 | B65: -FS | C65: 0 | D65: 0 | E65: 0 | F65: 0 | G65: 0 | H65: 0 | I65: 0 | J65: 0 | K65: 0 | L65: 0 | P65: =SUM(C65:O65) -> 0
... A71: 2.2.18 | B71: -P&D Material (for Tunnel) | C71: 0 | D71: 0 | E71: 0 | F71: 0 | G71: 0 | H71: 0 | I71: 0 | J71: 0 | K71: 0 | L71: 0 | P71: =SUM(C71:O71) -> 0
A72: 2.3 | B72: Plant & Machinery
A73: 2.3.1 | B73: -Plant, Equipments & Tools (purchased) | C73: 597.279 | D73: 0 | E73: 0 | F73: 0 | G73: 0 | H73: 0 | I73: 0 | J73: 0 | K73: 0 | L73: 0 | P73: =SUM(C73:O73) -> 597.279
A74: 2.3.2 | B74: -Plant, Equipments & Tools (external hire) | C74: 23929.473 | D74: 327.51 | E74: 0 | F74: 122.1742 | G74: 492.77 | H74: 0 | I74: -7594.666 | J74: 133.694 | K74: 186.8 | L74: 328.484 | P74: =SUM(C74:O74) -> 17926.239
A75: 2.3.3 | B75: -Diesel & Lubricant | C75: 867.66842 | D75: 12.3564 | E75: 6.8484 | F75: 0 | G75: 4.653 | H75: 0 | I75: 7.77294 | J75: 10.88363 | K75: 4.54394 | L75: 0 | P75: =SUM(C75:O75) -> 914.72673
A76: 2.3.4 | B76: -Repairing | C76: 0 | D76: 0 | E76: 0 | F76: 0 | G76: 0 | H76: 0 | I76: 0 | J76: 0 | K76: 0 | L76: 0 | P76: =SUM(C76:O76) -> 0
A77: 2.3.5 | B77: -Resale | C77: 0 | D77: 0 | E77: 0 | F77: 0 | G77: 0 | H77: 0 | I77: 0 | J77: 0 | K77: 0 | L77: 0 | P77: =SUM(C77:O77) -> 0
A78: 2.3.6 | B78: -Others Plant & Machinery | C78: 0 | D78: 0 | E78: 0 | F78: 0 | G78: 0 | H78: 0 | I78: 0 | J78: 0 | K78: 0 | L78: 0 | P78: =SUM(C78:O78) -> 0
A79: 2.3.7 | B79: -Depreciation (in Ledger) | C79: 985.28575 | D79: 3.84865 | E79: 3.84862 | F79: 3.84864 | G79: 2.74275 | H79: 2.74276 | I79: 2.74275 | J79: 0 | K79: 0 | L79: 0 | P79: =SUM(C79:O79) -> 1005.0599
A80: 2.3.8 | B80: -Potential Savings (Plants) | C80: 0 | D80: 0 | E80: 0 | F80: 0 | G80: 0 | H80: 0 | I80: 0 | J80: 0 | K80: 0 | L80: 0 | P80: =SUM(C80:O80) -> 0
A81: 2.3.9 | B81: - Plant, Equipments & Tools (internal hire) | C81: 0 | D81: 0 | E81: 0 | F81: 0 | G81: 0 | H81: 0 | I81: 0 | J81: 0 | K81: 0 | L81: 0 | P81: =SUM(C81:O81) -> 0
A82: 2.4 | B82: Subcontractor
A83: 2.4.1 | B83: -Contract Works | C83: 138399.35 | D83: 0 | E83: 0 | F83: 0 | G83: 0 | H83: 0 | I83: 0 | J83: 0 | K83: 0 | L83: 0 | P83: =SUM(C83:O83) -> 138399.35
A84: 2.4.2 | B84: -Variation | C84: 26374.747 | D84: 0 | E84: 376.073 | F84: 333.37735 | G84: 0 | H84: 0 | I84: 5783.4867 | J84: 0 | K84: 0 | L84: 0 | P84: =SUM(C84:O84) -> 32867.684
A85: 2.4.3 | B85: -Claim | C85: 0 | D85: 0 | E85: 0 | F85: 0 | G85: 0 | H85: 0 | I85: 0 | J85: 0 | K85: 0 | L85: 0 | P85: =SUM(C85:O85) -> 0
A86: 2.4.4 | B86: -Contra Charge | C86: 1869.6477 | D86: 0 | E86: 0 | F86: 0 | G86: 0 | H86: 0 | I86: -452.6215 | J86: 0 | K86: 0 | L86: 0 | P86: =SUM(C86:O86) -> 1417.0262
A87: 2.4.5 | B87: -Down Payment | C87: 243 | D87: 0 | E87: 0 | F87: 0 | G87: 0 | H87: 0 | I87: 0 | J87: 0 | K87: 0 | L87: 0 | P87: =SUM(C87:O87) -> 243
A88: 2.4.6 | B88: -Retention | C88: -7262.6488 | D88: 0 | E88: 0 | F88: 29.86141 | G88: 0 | H88: 0 | I88: -10.22647 | J88: 55.27568 | K88: 0 | L88: 0 | P88: =SUM(C88:O88) -> -7187.7382
A89: 2.4.7 | B89: -Potential Savings (DSC) | C89: 0 | D89: 0 | E89: 0 | F89: 0 | G89: 0 | H89: 0 | I89: 0 | J89: 0 | K89: 0 | L89: 0 | P89: =SUM(C89:O89) -> 0
A90: 2.4.8 | B90: -Commercial Settlement | C90: 0 | D90: 0 | E90: 0 | F90: 0 | G90: 0 | H90: 0 | I90: 0 | J90: 0 | K90: 0 | L90: 0 | P90: =SUM(C90:O90) -> 0
A91: 2.4.9 | B91: -Contract Works (for Tunnel) | C91: 0 | D91: 0 | E91: 0 | F91: 0 | G91: 0 | H91: 0 | I91: 0 | J91: 0 | K91: 0 | L91: 0 | P91: =SUM(C91:O91) -> 0
A92: 2.5 | B92: Manpower (Labour) for Works | C92: 0 | D92: 0 | E92: 0 | F92: 0 | G92: 0 | H92: 0 | I92: 0 | J92: 0 | K92: 0 | L92: 0 | P92: =SUM(C92:O92) -> 0
A93: 2.6 | B93: Nominated Package
A94: 2.6.1 | B94: -Nominated Subcontractor | C94: 0 | D94: 0 | E94: 0 | F94: 0 | G94: 0 | H94: 0 | I94: 0 | J94: 0 | K94: 0 | L94: 0 | P94: =SUM(C94:O94) -> 0
A95: 2.6.2 | B95: -Nominated Supplier | C95: 0 | D95: 0 | E95: 0 | F95: 0 | G95: 0 | H95: 0 | I95: 0 | J95: 0 | K95: 0 | L95: 0 | P95: =SUM(C95:O95) -> 0
A96: 2.7 | B96: Allow for Contingencies | C96: 0 | D96: 0 | E96: 0 | F96: 0 | G96: 0 | H96: 0 | I96: 0 | J96: 0 | K96: 0 | L96: 0 | P96: =SUM(C96:O96) -> 0
A97: 2.8 | B97: Allow for Defects Rectification Works | C97: 0 | D97: 0 | E97: 0 | F97: 0 | G97: 0 | H97: 0 | I97: 0 | J97: 0 | K97: 0 | L97: 0 | P97: =SUM(C97:O97) -> 0
A98: 2.9 | B98: Tender Fee | C98: 0 | D98: 0 | E98: 0 | F98: 0 | G98: 0 | H98: 0 | I98: 0 | J98: 0 | K98: 0 | L98: 0 | P98: =SUM(C98:O98) -> 0
A99: 2.10 | B99: Partialing Cost Total | C99: 0 | D99: 0 | E99: 0 | F99: 0 | G99: 0 | H99: 0 | I99: 0 | J99: 0 | K99: 0 | L99: 0 | P99: =SUM(C99:O99) -> 0
A100: 2.11 | B100: Incentive / POR Bonus
A101: 2.11.1 | B101: -Cost saving related bonus | C101: 0 | D101: 0 | E101: 0 | F101: 0 | G101: 0 | H101: 0 | I101: 0 | J101: 0 | K101: 0 | L101: 0 | P101: =SUM(C101:O101) -> 0
A102: 2.11.2 | B102: -Non-cost saving related bonus | C102: 0 | D102: 0 | E102: 0 | F102: 0 | G102: 0 | H102: 0 | I102: 0 | J102: 0 | K102: 0 | L102: 0 | P102: =SUM(C102:O102) -> 0
A103: 2.11.3 | B103: -Cost saving achieved | C103: 0 | D103: 0 | E103: 0 | F103: 0 | G103: 0 | H103: 0 | I103: 0 | J103: 0 | K103: 0 | L103: 0 | P103: =SUM(C103:O103) -> 0
A104: 2.12 | B104: CPR Penalty | C104: 0 | D104: 0 | E104: 0 | F104: 0 | G104: 0 | H104: 0 | I104: 0 | J104: 0 | K104: 0 | L104: 0 | P104: =SUM(C104:O104) -> 0
A105: 2.13 | B105: HO - Transformation Performance Fee | C105: 0 | D105: 0 | E105: 0 | F105: 0 | G105: 0 | H105: 0 | I105: 0 | J105: 0 | K105: 0 | L105: 0 | P105: =SUM(C105:O105) -> 0
A106: 2.14 | B106: Stretch Target (Cost) | C106: 0 | D106: 0 | E106: 0 | F106: 0 | G106: 0 | H106: 0 | I106: 0 | J106: 0 | K106: 0 | L106: 0 | P106: =SUM(C106:O106) -> 0
B107: Total Cost | C107: =SUM(C38:C106) -> 426441.42 | D107: =SUM(D38:D106) -> 414.85697 | E107: =SUM(E38:E106) -> 665.85216 | F107: =SUM(F38:F106) -> 683.93522 | G107: =SUM(G38:G106) -> 1096.1425 | H107: =SUM(H38:H106) -> 66.8613 | I107: =SUM(I38:I106) -> -9601.9539 | J107: =SUM(J38:J106) -> 296.88964 | ... P107: =SUM(P38:P106) -> 421787.52
A109: 3 | B109: Gross Profit (Item 1.0-2.0) (Financial A/C) | C109: =C36-C107 -> -550.73512 | D109: =D36-D107 -> -414.85697 | E109: =E36-E107 -> -665.85216 | F109: =F36-F107 -> -683.93522 | G109: =G36-G107 -> -1096.1425 | H109: =H36-H107 -> -66.8613 | I109: =I36-I107 -> 9601.9539 | J109: =J36-J107 -> -296.88964 | ... L109: =L36-L107 -> 1338.3725 | P109: =P36-P107 -> 6492.1705
...
